{"updated_at":"2026-04-21T02:13:49Z","data":{"USDJPY":[{"a":"titan_blade","s":0.0,"bid":158.966,"ask":158.966},{"a":"hfm_katana","s":0.4,"bid":158.973,"ask":158.977},{"a":"vantage_raw","s":0.4,"bid":158.973,"ask":158.977},{"a":"exness_pro","s":0.7,"bid":158.962,"ask":158.969},{"a":"axi_std","s":0.7,"bid":158.961,"ask":158.968},{"a":"icm_std","s":0.9,"bid":158.961,"ask":158.97},{"a":"exness_std","s":1.0,"bid":158.969,"ask":158.979},{"a":"titan_std","s":1.1,"bid":158.959,"ask":158.97},{"a":"xs_std","s":1.1,"bid":158.962,"ask":158.973},{"a":"three_pure","s":1.1,"bid":158.96,"ask":158.971},{"a":"xm_kiwami","s":1.3,"bid":158.968,"ask":158.981},{"a":"axiory_std","s":1.5,"bid":158.962,"ask":158.977},{"a":"fxgt_optimus","s":1.8,"bid":158.969,"ask":158.987},{"a":"vantage_std","s":2.0,"bid":158.967,"ask":158.987},{"a":"hfm_premium","s":2.2,"bid":158.956,"ask":158.978},{"a":"xm_std","s":2.3,"bid":158.963,"ask":158.986},{"a":"fxgt_std","s":2.5,"bid":158.956,"ask":158.981}],"EURUSD":[{"a":"vantage_raw","s":0.1,"bid":1.17806,"ask":1.17807},{"a":"titan_blade","s":0.2,"bid":1.17815,"ask":1.17817},{"a":"hfm_katana","s":0.5,"bid":1.17804,"ask":1.17809},{"a":"exness_pro","s":0.6,"bid":1.17813,"ask":1.17819},{"a":"axi_std","s":0.6,"bid":1.17813,"ask":1.17819},{"a":"three_pure","s":0.7,"bid":1.17812,"ask":1.17819},{"a":"exness_std","s":0.8,"bid":1.17806,"ask":1.17814},{"a":"icm_std","s":0.9,"bid":1.17811,"ask":1.1782},{"a":"xm_kiwami","s":1.0,"bid":1.17805,"ask":1.17815},{"a":"xs_std","s":1.0,"bid":1.17802,"ask":1.17812},{"a":"axiory_std","s":1.1,"bid":1.17808,"ask":1.17819},{"a":"titan_std","s":1.2,"bid":1.1781,"ask":1.17822},{"a":"vantage_std","s":1.4,"bid":1.178,"ask":1.17814},{"a":"fxgt_optimus","s":1.4,"bid":1.17799,"ask":1.17813},{"a":"xm_std","s":1.8,"bid":1.17797,"ask":1.17815},{"a":"fxgt_std","s":2.0,"bid":1.17797,"ask":1.17817},{"a":"hfm_premium","s":2.2,"bid":1.17804,"ask":1.17826}],"GBPUSD":[{"a":"vantage_raw","s":0.1,"bid":1.35256,"ask":1.35257},{"a":"titan_blade","s":0.2,"bid":1.35261,"ask":1.35263},{"a":"three_pure","s":0.6,"bid":1.3526,"ask":1.35266},{"a":"hfm_katana","s":0.7,"bid":1.35254,"ask":1.35261},{"a":"exness_pro","s":0.7,"bid":1.35254,"ask":1.35261},{"a":"axi_std","s":0.8,"bid":1.35262,"ask":1.3527},{"a":"icm_std","s":1.0,"bid":1.35256,"ask":1.35266},{"a":"exness_std","s":1.0,"bid":1.35254,"ask":1.35264},{"a":"xm_kiwami","s":1.2,"bid":1.35253,"ask":1.35265},{"a":"xs_std","s":1.2,"bid":1.35251,"ask":1.35263},{"a":"axiory_std","s":1.5,"bid":1.35257,"ask":1.35272},{"a":"fxgt_optimus","s":1.5,"bid":1.3525,"ask":1.35265},{"a":"titan_std","s":1.6,"bid":1.35257,"ask":1.35273},{"a":"vantage_std","s":1.9,"bid":1.35247,"ask":1.35266},{"a":"fxgt_std","s":1.9,"bid":1.35247,"ask":1.35266},{"a":"xm_std","s":2.2,"bid":1.35246,"ask":1.35268},{"a":"hfm_premium","s":2.3,"bid":1.35249,"ask":1.35272}],"AUDUSD":[{"a":"titan_blade","s":0.0,"bid":0.71758,"ask":0.71758},{"a":"vantage_raw","s":0.2,"bid":0.71762,"ask":0.71764},{"a":"hfm_katana","s":0.6,"bid":0.71761,"ask":0.71767},{"a":"exness_pro","s":0.6,"bid":0.7175,"ask":0.71756},{"a":"axi_std","s":0.7,"bid":0.71758,"ask":0.71765},{"a":"three_pure","s":0.7,"bid":0.71756,"ask":0.71763},{"a":"icm_std","s":0.9,"bid":0.71753,"ask":0.71762},{"a":"exness_std","s":0.9,"bid":0.71753,"ask":0.71762},{"a":"titan_std","s":1.1,"bid":0.71754,"ask":0.71765},{"a":"xs_std","s":1.1,"bid":0.71752,"ask":0.71763},{"a":"xm_kiwami","s":1.3,"bid":0.71752,"ask":0.71765},{"a":"fxgt_optimus","s":1.5,"bid":0.71757,"ask":0.71772},{"a":"axiory_std","s":1.7,"bid":0.71746,"ask":0.71763},{"a":"hfm_premium","s":1.7,"bid":0.7175,"ask":0.71767},{"a":"vantage_std","s":2.2,"bid":0.71743,"ask":0.71765},{"a":"fxgt_std","s":2.3,"bid":0.71745,"ask":0.71768},{"a":"xm_std","s":2.3,"bid":0.71752,"ask":0.71775}],"USDCHF":[{"a":"titan_blade","s":0.0,"bid":0.77878,"ask":0.77878},{"a":"vantage_raw","s":0.1,"bid":0.7788,"ask":0.77881},{"a":"three_pure","s":0.6,"bid":0.77873,"ask":0.77879},{"a":"hfm_katana","s":0.8,"bid":0.77877,"ask":0.77885},{"a":"axi_std","s":0.8,"bid":0.77872,"ask":0.7788},{"a":"icm_std","s":0.9,"bid":0.77873,"ask":0.77882},{"a":"exness_pro","s":0.9,"bid":0.77874,"ask":0.77883},{"a":"titan_std","s":1.0,"bid":0.7787,"ask":0.7788},{"a":"xs_std","s":1.1,"bid":0.77875,"ask":0.77886},{"a":"xm_kiwami","s":1.2,"bid":0.77874,"ask":0.77886},{"a":"exness_std","s":1.3,"bid":0.77875,"ask":0.77888},{"a":"fxgt_optimus","s":1.6,"bid":0.77873,"ask":0.77889},{"a":"vantage_std","s":1.9,"bid":0.77875,"ask":0.77894},{"a":"fxgt_std","s":2.0,"bid":0.77871,"ask":0.77891},{"a":"axiory_std","s":2.1,"bid":0.77867,"ask":0.77888},{"a":"hfm_premium","s":2.3,"bid":0.77867,"ask":0.7789},{"a":"xm_std","s":2.4,"bid":0.77868,"ask":0.77892}],"USDCAD":[{"a":"vantage_raw","s":0.0,"bid":1.36441,"ask":1.36441},{"a":"titan_blade","s":0.3,"bid":1.36436,"ask":1.36439},{"a":"axi_std","s":0.8,"bid":1.36437,"ask":1.36445},{"a":"three_pure","s":0.8,"bid":1.36434,"ask":1.36442},{"a":"icm_std","s":1.0,"bid":1.36435,"ask":1.36445},{"a":"hfm_katana","s":1.0,"bid":1.36436,"ask":1.36446},{"a":"exness_pro","s":1.0,"bid":1.36435,"ask":1.36445},{"a":"titan_std","s":1.3,"bid":1.36431,"ask":1.36444},{"a":"exness_std","s":1.4,"bid":1.36432,"ask":1.36446},{"a":"fxgt_optimus","s":1.5,"bid":1.36433,"ask":1.36448},{"a":"xs_std","s":1.6,"bid":1.36432,"ask":1.36448},{"a":"axiory_std","s":2.2,"bid":1.3642,"ask":1.36442},{"a":"vantage_std","s":2.2,"bid":1.36431,"ask":1.36453},{"a":"xm_kiwami","s":2.3,"bid":1.36427,"ask":1.3645},{"a":"hfm_premium","s":2.3,"bid":1.36427,"ask":1.3645},{"a":"fxgt_std","s":2.8,"bid":1.36426,"ask":1.36454},{"a":"xm_std","s":3.0,"bid":1.36425,"ask":1.36455}],"EURJPY":[{"a":"vantage_raw","s":0.1,"bid":187.282,"ask":187.283},{"a":"titan_blade","s":0.3,"bid":187.285,"ask":187.288},{"a":"three_pure","s":0.8,"bid":187.283,"ask":187.291},{"a":"axi_std","s":1.0,"bid":187.281,"ask":187.291},{"a":"exness_pro","s":1.1,"bid":187.278,"ask":187.289},{"a":"titan_std","s":1.4,"bid":187.279,"ask":187.293},{"a":"hfm_katana","s":1.5,"bid":187.271,"ask":187.286},{"a":"xs_std","s":1.5,"bid":187.268,"ask":187.283},{"a":"icm_std","s":1.6,"bid":187.278,"ask":187.294},{"a":"axiory_std","s":1.6,"bid":187.282,"ask":187.298},{"a":"exness_std","s":1.6,"bid":187.278,"ask":187.294},{"a":"xm_kiwami","s":2.2,"bid":187.278,"ask":187.3},{"a":"fxgt_optimus","s":2.6,"bid":187.273,"ask":187.299},{"a":"hfm_premium","s":2.6,"bid":187.273,"ask":187.299},{"a":"xm_std","s":2.9,"bid":187.268,"ask":187.297},{"a":"vantage_std","s":3.0,"bid":187.271,"ask":187.301},{"a":"fxgt_std","s":3.5,"bid":187.26,"ask":187.295}],"GBPJPY":[{"a":"vantage_raw","s":0.9,"bid":215.019,"ask":215.028},{"a":"titan_blade","s":1.0,"bid":215.015,"ask":215.025},{"a":"axi_std","s":1.2,"bid":215.018,"ask":215.03},{"a":"hfm_katana","s":1.5,"bid":215.014,"ask":215.029},{"a":"icm_std","s":1.7,"bid":215.009,"ask":215.026},{"a":"exness_pro","s":1.9,"bid":215.005,"ask":215.024},{"a":"three_pure","s":1.9,"bid":215.012,"ask":215.031},{"a":"xs_std","s":2.0,"bid":215.005,"ask":215.025},{"a":"axiory_std","s":2.5,"bid":215.019,"ask":215.044},{"a":"xm_kiwami","s":2.7,"bid":215.014,"ask":215.041},{"a":"titan_std","s":2.7,"bid":215.009,"ask":215.036},{"a":"exness_std","s":2.7,"bid":215.016,"ask":215.043},{"a":"fxgt_optimus","s":2.8,"bid":215.013,"ask":215.041},{"a":"fxgt_std","s":3.2,"bid":214.998,"ask":215.03},{"a":"xm_std","s":3.3,"bid":215.007,"ask":215.04},{"a":"hfm_premium","s":4.3,"bid":215.001,"ask":215.044},{"a":"vantage_std","s":5.1,"bid":215.001,"ask":215.052}],"AUDJPY":[{"a":"titan_blade","s":0.2,"bid":114.07,"ask":114.072},{"a":"vantage_raw","s":0.3,"bid":114.084,"ask":114.087},{"a":"three_pure","s":1.0,"bid":114.07,"ask":114.08},{"a":"axi_std","s":1.1,"bid":114.072,"ask":114.083},{"a":"icm_std","s":1.3,"bid":114.063,"ask":114.076},{"a":"hfm_katana","s":1.3,"bid":114.08,"ask":114.093},{"a":"exness_pro","s":1.3,"bid":114.058,"ask":114.071},{"a":"titan_std","s":1.5,"bid":114.062,"ask":114.077},{"a":"axiory_std","s":1.8,"bid":114.065,"ask":114.083},{"a":"xs_std","s":1.9,"bid":114.061,"ask":114.08},{"a":"exness_std","s":1.9,"bid":114.068,"ask":114.087},{"a":"xm_kiwami","s":2.4,"bid":114.065,"ask":114.089},{"a":"fxgt_optimus","s":2.6,"bid":114.077,"ask":114.103},{"a":"hfm_premium","s":3.0,"bid":114.057,"ask":114.087},{"a":"vantage_std","s":3.1,"bid":114.056,"ask":114.087},{"a":"fxgt_std","s":3.3,"bid":114.053,"ask":114.086},{"a":"xm_std","s":3.3,"bid":114.069,"ask":114.102}],"XAUUSD":[{"a":"hfm_katana","s":0.8,"bid":4809.45,"ask":4809.53},{"a":"three_pure","s":1.5,"bid":4807.71,"ask":4807.86},{"a":"vantage_raw","s":1.5,"bid":4809.2,"ask":4809.35},{"a":"titan_blade","s":1.5,"bid":4807.3,"ask":4807.45},{"a":"axi_std","s":1.6,"bid":4807.6,"ask":4807.76},{"a":"xs_std","s":1.9,"bid":4807.11,"ask":4807.3},{"a":"exness_pro","s":2.0,"bid":4807.237,"ask":4807.433},{"a":"icm_std","s":2.2,"bid":4807.19,"ask":4807.41},{"a":"titan_std","s":2.3,"bid":4807.59,"ask":4807.82},{"a":"xm_kiwami","s":2.8,"bid":4808.97,"ask":4809.25},{"a":"fxgt_optimus","s":3.3,"bid":4809.36,"ask":4809.69},{"a":"exness_std","s":3.6,"bid":4808.272,"ask":4808.632},{"a":"hfm_premium","s":3.9,"bid":4807.8,"ask":4808.19},{"a":"fxgt_std","s":4.1,"bid":4807.03,"ask":4807.44},{"a":"vantage_std","s":4.3,"bid":4807.03,"ask":4807.46},{"a":"xm_std","s":5.0,"bid":4809.33,"ask":4809.83},{"a":"axiory_std","s":8.7,"bid":4806.64,"ask":4807.51}],"XAGUSD":[{"a":"exness_pro","s":21.0,"bid":79.394,"ask":79.415},{"a":"icm_std","s":30.0,"bid":79.378,"ask":79.408},{"a":"exness_std","s":30.0,"bid":79.438,"ask":79.468},{"a":"axi_std","s":32.0,"bid":79.397,"ask":79.429},{"a":"vantage_raw","s":33.0,"bid":79.418,"ask":79.451},{"a":"hfm_katana","s":39.0,"bid":79.425,"ask":79.464},{"a":"vantage_std","s":44.0,"bid":79.39,"ask":79.434},{"a":"xm_kiwami","s":51.0,"bid":79.43,"ask":79.481},{"a":"xs_std","s":56.0,"bid":79.368,"ask":79.424},{"a":"titan_blade","s":62.0,"bid":79.379,"ask":79.441},{"a":"titan_std","s":63.0,"bid":79.378,"ask":79.441},{"a":"three_pure","s":70.0,"bid":79.376,"ask":79.446},{"a":"xm_std","s":71.0,"bid":79.408,"ask":79.479},{"a":"fxgt_optimus","s":75.0,"bid":79.41,"ask":79.485},{"a":"hfm_premium","s":83.0,"bid":79.366,"ask":79.449},{"a":"axiory_std","s":96.0,"bid":79.321,"ask":79.417},{"a":"fxgt_std","s":99.0,"bid":79.347,"ask":79.446}],"BTCUSD":[{"a":"exness_pro","s":9.8,"bid":75737.77,"ask":75747.57},{"a":"hfm_katana","s":10.0,"bid":75751.155,"ask":75761.145},{"a":"icm_std","s":12.0,"bid":75730.21,"ask":75742.21},{"a":"axi_std","s":12.0,"bid":75743.85,"ask":75755.85},{"a":"exness_std","s":14.0,"bid":75789.54,"ask":75803.54},{"a":"three_pure","s":19.0,"bid":75728.0,"ask":75747.0},{"a":"xm_kiwami","s":22.5,"bid":75762.8,"ask":75785.3},{"a":"vantage_raw","s":25.0,"bid":75773.76,"ask":75798.78},{"a":"vantage_std","s":25.1,"bid":75751.6,"ask":75776.72},{"a":"xs_std","s":27.0,"bid":75703.9,"ask":75730.9},{"a":"fxgt_optimus","s":39.0,"bid":75795.82,"ask":75834.77},{"a":"titan_blade","s":40.4,"bid":75718.8,"ask":75759.2},{"a":"fxgt_std","s":42.6,"bid":75732.23,"ask":75774.86},{"a":"titan_std","s":43.7,"bid":75722.7,"ask":75766.4},{"a":"xm_std","s":50.0,"bid":75765.15,"ask":75815.15},{"a":"hfm_premium","s":62.0,"bid":75672.615,"ask":75734.615}],"ETHUSD":[{"a":"hfm_katana","s":1.0,"bid":2308.216,"ask":2309.215},{"a":"exness_pro","s":1.0,"bid":2310.07,"ask":2311.05},{"a":"axi_std","s":1.3,"bid":2310.52,"ask":2311.77},{"a":"exness_std","s":1.4,"bid":2311.5,"ask":2312.9},{"a":"three_pure","s":2.1,"bid":2309.6,"ask":2311.7},{"a":"fxgt_optimus","s":2.2,"bid":2308.91,"ask":2311.15},{"a":"vantage_std","s":2.5,"bid":2309.13,"ask":2311.66},{"a":"vantage_raw","s":2.5,"bid":2308.64,"ask":2311.14},{"a":"icm_std","s":2.9,"bid":2309.42,"ask":2312.32},{"a":"fxgt_std","s":3.2,"bid":2307.84,"ask":2311.05},{"a":"xm_kiwami","s":3.5,"bid":2309.13,"ask":2312.58},{"a":"xs_std","s":4.6,"bid":2305.88,"ask":2310.48},{"a":"hfm_premium","s":4.9,"bid":2306.925,"ask":2311.785},{"a":"xm_std","s":4.9,"bid":2307.21,"ask":2312.11},{"a":"titan_std","s":7.5,"bid":2307.2,"ask":2314.7},{"a":"titan_blade","s":7.5,"bid":2306.9,"ask":2314.39}],"US30":[{"a":"icm_std","s":1.2,"bid":49531.9,"ask":49533.1},{"a":"axi_std","s":1.2,"bid":49531.85,"ask":49533.05},{"a":"exness_pro","s":1.5,"bid":49577.5,"ask":49579.0},{"a":"hfm_katana","s":1.9,"bid":49581.0,"ask":49582.9},{"a":"xs_std","s":2.0,"bid":49531.45,"ask":49533.45},{"a":"exness_std","s":2.1,"bid":49579.7,"ask":49581.8},{"a":"fxgt_optimus","s":2.8,"bid":49535.56,"ask":49538.34},{"a":"three_pure","s":3.0,"bid":49570.0,"ask":49573.0},{"a":"titan_blade","s":3.0,"bid":49570.4,"ask":49573.4},{"a":"vantage_std","s":3.1,"bid":49576.47,"ask":49579.57},{"a":"vantage_raw","s":3.1,"bid":49579.47,"ask":49582.57},{"a":"xm_kiwami","s":3.9,"bid":49537.05,"ask":49540.95},{"a":"titan_std","s":4.2,"bid":49570.0,"ask":49574.2},{"a":"fxgt_std","s":4.5,"bid":49530.23,"ask":49534.73},{"a":"axiory_std","s":5.4,"bid":49568.19,"ask":49573.59},{"a":"xm_std","s":5.5,"bid":49537.75,"ask":49543.25},{"a":"hfm_premium","s":6.8,"bid":49724.05,"ask":49730.86}],"US500":[{"a":"axi_std","s":2.9,"bid":7122.51,"ask":7122.8},{"a":"exness_pro","s":4.5,"bid":7131.58,"ask":7132.03},{"a":"icm_std","s":5.0,"bid":7122.4,"ask":7122.9},{"a":"three_pure","s":5.0,"bid":7128.3,"ask":7128.8},{"a":"hfm_premium","s":5.0,"bid":7133.35,"ask":7133.85},{"a":"xm_kiwami","s":5.5,"bid":7122.86,"ask":7123.41},{"a":"vantage_std","s":6.0,"bid":7131.31,"ask":7131.91},{"a":"vantage_raw","s":6.0,"bid":7132.18,"ask":7132.78},{"a":"hfm_katana","s":6.2,"bid":7134.53,"ask":7135.15},{"a":"exness_std","s":6.4,"bid":7131.8,"ask":7132.44},{"a":"xm_std","s":7.0,"bid":7123.4,"ask":7124.1},{"a":"axiory_std","s":7.6,"bid":7127.96,"ask":7128.72},{"a":"titan_blade","s":8.0,"bid":7128.2,"ask":7129.0},{"a":"xs_std","s":11.0,"bid":7122.1,"ask":7123.2},{"a":"titan_std","s":21.0,"bid":7127.8,"ask":7129.9},{"a":"fxgt_optimus","s":21.2,"bid":7122.59,"ask":7124.71},{"a":"fxgt_std","s":55.4,"bid":7119.88,"ask":7125.42}],"US100":[{"a":"icm_std","s":1.0,"bid":26661.9,"ask":26662.9},{"a":"titan_blade","s":1.0,"bid":26683.0,"ask":26684.0},{"a":"hfm_katana","s":1.5,"bid":26690.8,"ask":26692.3},{"a":"exness_pro","s":1.5,"bid":26696.69,"ask":26698.2},{"a":"vantage_std","s":1.8,"bid":26695.06,"ask":26696.86},{"a":"vantage_raw","s":1.8,"bid":26698.56,"ask":26700.36},{"a":"xs_std","s":1.9,"bid":26660.5,"ask":26662.4},{"a":"xm_kiwami","s":2.0,"bid":26662.77,"ask":26664.72},{"a":"three_pure","s":2.0,"bid":26682.0,"ask":26684.0},{"a":"hfm_premium","s":2.1,"bid":26686.0,"ask":26688.1},{"a":"titan_std","s":2.2,"bid":26682.6,"ask":26684.8},{"a":"exness_std","s":2.2,"bid":26696.45,"ask":26698.61},{"a":"axiory_std","s":2.3,"bid":26681.32,"ask":26683.62},{"a":"axi_std","s":2.5,"bid":26815.25,"ask":26817.75},{"a":"xm_std","s":2.6,"bid":26664.58,"ask":26667.18},{"a":"fxgt_optimus","s":2.9,"bid":26664.6,"ask":26667.45},{"a":"fxgt_std","s":3.4,"bid":26659.64,"ask":26663.04}],"JP225":[{"a":"icm_std","s":2.0,"bid":59455.0,"ask":59457.0},{"a":"exness_pro","s":2.1,"bid":59489.9,"ask":59492.0},{"a":"exness_std","s":3.0,"bid":59488.7,"ask":59491.7},{"a":"axi_std","s":5.0,"bid":59461.25,"ask":59466.25},{"a":"xm_kiwami","s":6.0,"bid":59456.0,"ask":59462.0},{"a":"xm_std","s":8.0,"bid":59480.0,"ask":59488.0},{"a":"titan_blade","s":8.0,"bid":59471.1,"ask":59479.1},{"a":"titan_std","s":9.2,"bid":59470.5,"ask":59479.7},{"a":"xs_std","s":10.0,"bid":59451.0,"ask":59461.0},{"a":"fxgt_optimus","s":10.0,"bid":59477.0,"ask":59487.0},{"a":"axiory_std","s":11.0,"bid":59464.56,"ask":59475.56},{"a":"vantage_std","s":11.0,"bid":59480.33,"ask":59491.33},{"a":"vantage_raw","s":11.0,"bid":59495.33,"ask":59506.33},{"a":"hfm_katana","s":11.2,"bid":59505.4,"ask":59516.6},{"a":"fxgt_std","s":12.0,"bid":59451.0,"ask":59463.0},{"a":"three_pure","s":16.0,"bid":59465.0,"ask":59481.0},{"a":"hfm_premium","s":16.0,"bid":59478.0,"ask":59494.0}],"CRUDE":[{"a":"exness_pro","s":1.4,"bid":86.212,"ask":86.226},{"a":"icm_std","s":2.0,"bid":89.24,"ask":89.26},{"a":"exness_std","s":2.0,"bid":86.22,"ask":86.24},{"a":"axi_std","s":2.5,"bid":86.228,"ask":86.253},{"a":"xm_kiwami","s":3.0,"bid":89.43,"ask":89.46},{"a":"xs_std","s":3.8,"bid":89.224,"ask":89.262},{"a":"xm_std","s":5.0,"bid":89.44,"ask":89.49},{"a":"titan_blade","s":6.0,"bid":89.22,"ask":89.28},{"a":"vantage_raw","s":6.7,"bid":89.25,"ask":89.317},{"a":"titan_std","s":7.0,"bid":89.21,"ask":89.28},{"a":"vantage_std","s":7.3,"bid":89.222,"ask":89.295},{"a":"axiory_std","s":7.6,"bid":90.216,"ask":90.292},{"a":"three_pure","s":9.0,"bid":90.2,"ask":90.29},{"a":"hfm_katana","s":11.0,"bid":89.22,"ask":89.33},{"a":"hfm_premium","s":12.0,"bid":86.62,"ask":86.74},{"a":"fxgt_optimus","s":15.0,"bid":89.21,"ask":89.36},{"a":"fxgt_std","s":19.0,"bid":89.16,"ask":89.35}],"NGAS":[{"a":"icm_std","s":1.0,"bid":2.661,"ask":2.662},{"a":"exness_pro","s":7.6,"bid":2.8037,"ask":2.8113},{"a":"exness_std","s":10.9,"bid":2.8021,"ask":2.813},{"a":"vantage_std","s":12.0,"bid":2.671,"ask":2.683},{"a":"axi_std","s":12.0,"bid":2.801,"ask":2.813},{"a":"vantage_raw","s":12.0,"bid":2.672,"ask":2.684},{"a":"xm_kiwami","s":16.0,"bid":2.668,"ask":2.684},{"a":"titan_blade","s":17.0,"bid":2.653,"ask":2.67},{"a":"titan_std","s":18.0,"bid":2.652,"ask":2.67},{"a":"xm_std","s":21.0,"bid":2.667,"ask":2.688},{"a":"fxgt_optimus","s":38.0,"bid":2.8,"ask":2.838},{"a":"axiory_std","s":40.0,"bid":2.788,"ask":2.828},{"a":"xs_std","s":52.0,"bid":2.781,"ask":2.833},{"a":"fxgt_std","s":63.0,"bid":2.785,"ask":2.848}]}}