{"updated_at":"2026-04-15T14:58:50Z","data":{"USDJPY":[{"a":"titan_blade","s":0.1,"bid":159.0,"ask":159.001},{"a":"axi_std","s":0.7,"bid":159.001,"ask":159.008},{"a":"exness_pro","s":0.7,"bid":159.031,"ask":159.038},{"a":"three_pure","s":0.9,"bid":159.025,"ask":159.034},{"a":"icm_std","s":0.9,"bid":158.972,"ask":158.981},{"a":"exness_std","s":1.0,"bid":158.996,"ask":159.006},{"a":"xs_std","s":1.1,"bid":159.023,"ask":159.034},{"a":"xm_kiwami","s":1.2,"bid":158.993,"ask":159.005},{"a":"titan_std","s":1.2,"bid":158.972,"ask":158.984},{"a":"axiory_std","s":1.5,"bid":158.999,"ask":159.014},{"a":"vantage_std","s":2.0,"bid":158.98,"ask":159.0},{"a":"hfm_premium","s":2.2,"bid":159.024,"ask":159.046},{"a":"xm_std","s":2.4,"bid":158.987,"ask":159.011},{"a":"fxgt_std","s":2.6,"bid":158.979,"ask":159.005}],"EURUSD":[{"a":"titan_blade","s":0.1,"bid":1.17973,"ask":1.17974},{"a":"exness_pro","s":0.6,"bid":1.17943,"ask":1.17949},{"a":"axi_std","s":0.7,"bid":1.17964,"ask":1.17971},{"a":"exness_std","s":0.8,"bid":1.17965,"ask":1.17973},{"a":"three_pure","s":0.8,"bid":1.17938,"ask":1.17946},{"a":"icm_std","s":0.8,"bid":1.17981,"ask":1.17989},{"a":"xm_kiwami","s":0.9,"bid":1.17962,"ask":1.17971},{"a":"xs_std","s":1.1,"bid":1.1794,"ask":1.17951},{"a":"titan_std","s":1.1,"bid":1.17974,"ask":1.17985},{"a":"vantage_std","s":1.3,"bid":1.17971,"ask":1.17984},{"a":"axiory_std","s":1.5,"bid":1.17959,"ask":1.17974},{"a":"hfm_premium","s":1.7,"bid":1.17933,"ask":1.1795},{"a":"xm_std","s":1.8,"bid":1.17958,"ask":1.17976},{"a":"fxgt_std","s":1.9,"bid":1.17958,"ask":1.17977}],"GBPUSD":[{"a":"titan_blade","s":0.5,"bid":1.35693,"ask":1.35698},{"a":"exness_pro","s":0.7,"bid":1.35671,"ask":1.35678},{"a":"three_pure","s":0.8,"bid":1.35667,"ask":1.35675},{"a":"axi_std","s":0.8,"bid":1.35694,"ask":1.35702},{"a":"xm_kiwami","s":0.9,"bid":1.35695,"ask":1.35704},{"a":"icm_std","s":0.9,"bid":1.3571,"ask":1.35719},{"a":"exness_std","s":1.0,"bid":1.35698,"ask":1.35708},{"a":"xs_std","s":1.0,"bid":1.3567,"ask":1.3568},{"a":"axiory_std","s":1.5,"bid":1.35686,"ask":1.35701},{"a":"titan_std","s":1.6,"bid":1.35689,"ask":1.35705},{"a":"vantage_std","s":1.9,"bid":1.35686,"ask":1.35705},{"a":"fxgt_std","s":1.9,"bid":1.35692,"ask":1.35711},{"a":"hfm_premium","s":1.9,"bid":1.35656,"ask":1.35675},{"a":"xm_std","s":2.0,"bid":1.35689,"ask":1.35709}],"AUDUSD":[{"a":"titan_blade","s":0.0,"bid":0.71566,"ask":0.71566},{"a":"exness_pro","s":0.6,"bid":0.71537,"ask":0.71543},{"a":"axi_std","s":0.7,"bid":0.71559,"ask":0.71566},{"a":"three_pure","s":0.8,"bid":0.71543,"ask":0.71551},{"a":"icm_std","s":0.8,"bid":0.71569,"ask":0.71577},{"a":"exness_std","s":0.9,"bid":0.71564,"ask":0.71573},{"a":"xs_std","s":1.0,"bid":0.71538,"ask":0.71548},{"a":"titan_std","s":1.1,"bid":0.7156,"ask":0.71571},{"a":"xm_kiwami","s":1.4,"bid":0.71559,"ask":0.71573},{"a":"hfm_premium","s":1.6,"bid":0.7153,"ask":0.71546},{"a":"axiory_std","s":1.7,"bid":0.71553,"ask":0.7157},{"a":"vantage_std","s":2.1,"bid":0.71555,"ask":0.71576},{"a":"fxgt_std","s":2.2,"bid":0.7155,"ask":0.71572},{"a":"xm_std","s":2.4,"bid":0.71554,"ask":0.71578}],"USDCHF":[{"a":"titan_blade","s":0.0,"bid":0.78161,"ask":0.78161},{"a":"three_pure","s":0.8,"bid":0.7815,"ask":0.78158},{"a":"axi_std","s":0.8,"bid":0.78132,"ask":0.7814},{"a":"exness_pro","s":0.9,"bid":0.78139,"ask":0.78148},{"a":"xs_std","s":1.0,"bid":0.78141,"ask":0.78151},{"a":"titan_std","s":1.0,"bid":0.78159,"ask":0.78169},{"a":"xm_kiwami","s":1.1,"bid":0.78124,"ask":0.78135},{"a":"icm_std","s":1.1,"bid":0.78156,"ask":0.78167},{"a":"exness_std","s":1.3,"bid":0.78126,"ask":0.78139},{"a":"hfm_premium","s":1.8,"bid":0.78137,"ask":0.78155},{"a":"axiory_std","s":1.9,"bid":0.78125,"ask":0.78144},{"a":"vantage_std","s":2.0,"bid":0.78143,"ask":0.78163},{"a":"fxgt_std","s":2.0,"bid":0.78126,"ask":0.78146},{"a":"xm_std","s":2.2,"bid":0.78118,"ask":0.7814}],"USDCAD":[{"a":"titan_blade","s":0.1,"bid":1.3747,"ask":1.37471},{"a":"three_pure","s":0.8,"bid":1.37505,"ask":1.37513},{"a":"axi_std","s":0.8,"bid":1.37494,"ask":1.37502},{"a":"icm_std","s":1.0,"bid":1.37473,"ask":1.37483},{"a":"exness_pro","s":1.0,"bid":1.37505,"ask":1.37515},{"a":"titan_std","s":1.1,"bid":1.37476,"ask":1.37487},{"a":"exness_std","s":1.4,"bid":1.37482,"ask":1.37496},{"a":"xs_std","s":1.4,"bid":1.37495,"ask":1.37509},{"a":"axiory_std","s":1.7,"bid":1.37481,"ask":1.37498},{"a":"xm_kiwami","s":2.0,"bid":1.37478,"ask":1.37498},{"a":"vantage_std","s":2.3,"bid":1.3747,"ask":1.37493},{"a":"hfm_premium","s":2.4,"bid":1.37509,"ask":1.37533},{"a":"xm_std","s":2.8,"bid":1.37474,"ask":1.37502},{"a":"fxgt_std","s":3.0,"bid":1.37477,"ask":1.37507}],"EURJPY":[{"a":"titan_blade","s":0.5,"bid":187.58,"ask":187.585},{"a":"three_pure","s":0.9,"bid":187.558,"ask":187.567},{"a":"axi_std","s":1.0,"bid":187.565,"ask":187.575},{"a":"exness_pro","s":1.1,"bid":187.569,"ask":187.58},{"a":"xs_std","s":1.3,"bid":187.56,"ask":187.573},{"a":"titan_std","s":1.5,"bid":187.557,"ask":187.572},{"a":"exness_std","s":1.6,"bid":187.563,"ask":187.579},{"a":"axiory_std","s":1.7,"bid":187.565,"ask":187.582},{"a":"icm_std","s":1.8,"bid":187.56,"ask":187.578},{"a":"xm_kiwami","s":2.1,"bid":187.553,"ask":187.574},{"a":"hfm_premium","s":2.6,"bid":187.555,"ask":187.581},{"a":"vantage_std","s":3.0,"bid":187.556,"ask":187.586},{"a":"fxgt_std","s":3.3,"bid":187.542,"ask":187.575}],"GBPJPY":[{"a":"three_pure","s":1.3,"bid":215.751,"ask":215.764},{"a":"axi_std","s":1.4,"bid":215.757,"ask":215.771},{"a":"icm_std","s":1.5,"bid":215.746,"ask":215.761},{"a":"titan_blade","s":1.6,"bid":215.748,"ask":215.764},{"a":"xs_std","s":1.9,"bid":215.753,"ask":215.772},{"a":"exness_pro","s":1.9,"bid":215.754,"ask":215.773},{"a":"axiory_std","s":2.0,"bid":215.744,"ask":215.764},{"a":"xm_kiwami","s":2.4,"bid":215.749,"ask":215.773},{"a":"exness_std","s":2.7,"bid":215.757,"ask":215.784},{"a":"titan_std","s":2.8,"bid":215.714,"ask":215.742},{"a":"hfm_premium","s":2.9,"bid":215.741,"ask":215.77},{"a":"fxgt_std","s":3.6,"bid":215.735,"ask":215.771},{"a":"vantage_std","s":5.1,"bid":215.715,"ask":215.766}],"AUDJPY":[{"a":"titan_blade","s":0.4,"bid":113.79,"ask":113.794},{"a":"three_pure","s":0.9,"bid":113.778,"ask":113.787},{"a":"axi_std","s":1.1,"bid":113.789,"ask":113.8},{"a":"icm_std","s":1.1,"bid":113.78,"ask":113.791},{"a":"exness_pro","s":1.3,"bid":113.766,"ask":113.779},{"a":"titan_std","s":1.4,"bid":113.769,"ask":113.783},{"a":"xs_std","s":1.8,"bid":113.765,"ask":113.783},{"a":"exness_std","s":1.9,"bid":113.785,"ask":113.804},{"a":"axiory_std","s":1.9,"bid":113.785,"ask":113.804},{"a":"xm_kiwami","s":2.2,"bid":113.777,"ask":113.799},{"a":"hfm_premium","s":2.8,"bid":113.756,"ask":113.784},{"a":"vantage_std","s":3.1,"bid":113.765,"ask":113.796},{"a":"fxgt_std","s":3.5,"bid":113.76,"ask":113.795}],"XAUUSD":[{"a":"titan_std","s":1.2,"bid":4818.32,"ask":4818.44},{"a":"titan_blade","s":1.2,"bid":4816.68,"ask":4816.8},{"a":"three_pure","s":1.5,"bid":4814.81,"ask":4814.96},{"a":"axi_std","s":1.6,"bid":4815.29,"ask":4815.45},{"a":"xs_std","s":1.9,"bid":4814.73,"ask":4814.92},{"a":"icm_std","s":2.0,"bid":4818.26,"ask":4818.46},{"a":"exness_pro","s":2.0,"bid":4814.65,"ask":4814.846},{"a":"exness_std","s":2.8,"bid":4816.081,"ask":4816.361},{"a":"xm_kiwami","s":2.9,"bid":4816.0,"ask":4816.29},{"a":"hfm_premium","s":3.5,"bid":4814.53,"ask":4814.88},{"a":"fxgt_std","s":3.7,"bid":4816.29,"ask":4816.66},{"a":"vantage_std","s":4.3,"bid":4817.82,"ask":4818.25},{"a":"axiory_std","s":9.3,"bid":4815.21,"ask":4816.14}],"XAGUSD":[{"a":"exness_pro","s":21.0,"bid":79.991,"ask":80.012},{"a":"axi_std","s":26.0,"bid":80.001,"ask":80.027},{"a":"exness_std","s":30.0,"bid":80.022,"ask":80.052},{"a":"icm_std","s":30.0,"bid":80.073,"ask":80.103},{"a":"vantage_std","s":35.0,"bid":80.07,"ask":80.105},{"a":"xm_kiwami","s":51.0,"bid":80.004,"ask":80.055},{"a":"xs_std","s":51.0,"bid":79.996,"ask":80.047},{"a":"titan_std","s":53.0,"bid":80.078,"ask":80.131},{"a":"titan_blade","s":61.0,"bid":79.998,"ask":80.059},{"a":"axiory_std","s":71.0,"bid":80.004,"ask":80.075},{"a":"three_pure","s":71.0,"bid":79.973,"ask":80.044},{"a":"fxgt_std","s":80.0,"bid":80.001,"ask":80.081},{"a":"hfm_premium","s":94.0,"bid":79.97,"ask":80.064}],"BTCUSD":[{"a":"exness_pro","s":9.8,"bid":74128.19,"ask":74137.99},{"a":"axi_std","s":12.0,"bid":74176.55,"ask":74188.55},{"a":"icm_std","s":12.0,"bid":74212.22,"ask":74224.22},{"a":"exness_std","s":14.0,"bid":74171.72,"ask":74185.72},{"a":"three_pure","s":19.0,"bid":74192.0,"ask":74211.0},{"a":"xm_kiwami","s":22.5,"bid":74220.7,"ask":74243.2},{"a":"vantage_std","s":25.0,"bid":74159.47,"ask":74184.45},{"a":"fxgt_std","s":36.8,"bid":74255.93,"ask":74292.69},{"a":"xs_std","s":37.0,"bid":74116.41,"ask":74153.41},{"a":"titan_std","s":42.8,"bid":74195.1,"ask":74237.9},{"a":"titan_blade","s":43.4,"bid":74161.8,"ask":74205.2},{"a":"hfm_premium","s":62.0,"bid":74083.875,"ask":74145.875}],"ETHUSD":[{"a":"exness_pro","s":1.0,"bid":2336.05,"ask":2337.03},{"a":"axi_std","s":1.3,"bid":2337.185,"ask":2338.435},{"a":"exness_std","s":1.4,"bid":2337.0,"ask":2338.4},{"a":"three_pure","s":2.3,"bid":2337.3,"ask":2339.6},{"a":"vantage_std","s":2.5,"bid":2336.7,"ask":2339.17},{"a":"icm_std","s":2.9,"bid":2338.11,"ask":2341.01},{"a":"fxgt_std","s":3.1,"bid":2338.06,"ask":2341.15},{"a":"xm_kiwami","s":3.5,"bid":2337.71,"ask":2341.16},{"a":"xs_std","s":4.6,"bid":2333.34,"ask":2337.94},{"a":"hfm_premium","s":4.9,"bid":2333.415,"ask":2338.275},{"a":"titan_std","s":7.5,"bid":2336.0,"ask":2343.45},{"a":"titan_blade","s":7.5,"bid":2334.9,"ask":2342.4}],"US30":[{"a":"icm_std","s":0.7,"bid":48353.7,"ask":48354.4},{"a":"axi_std","s":0.8,"bid":48331.6,"ask":48332.4},{"a":"exness_pro","s":1.5,"bid":48385.5,"ask":48387.0},{"a":"xs_std","s":2.0,"bid":48338.0,"ask":48340.0},{"a":"three_pure","s":2.0,"bid":48365.0,"ask":48367.0},{"a":"titan_blade","s":2.0,"bid":48373.2,"ask":48375.2},{"a":"exness_std","s":2.1,"bid":48374.5,"ask":48376.6},{"a":"vantage_std","s":3.1,"bid":48387.48,"ask":48390.58},{"a":"titan_std","s":3.2,"bid":48376.6,"ask":48379.8},{"a":"xm_kiwami","s":3.9,"bid":48341.05,"ask":48344.95},{"a":"axiory_std","s":4.2,"bid":48355.05,"ask":48359.25},{"a":"fxgt_std","s":4.5,"bid":48338.84,"ask":48343.34},{"a":"hfm_premium","s":6.8,"bid":48557.08,"ask":48563.89}],"US500":[{"a":"axi_std","s":2.9,"bid":6991.01,"ask":6991.3},{"a":"icm_std","s":3.0,"bid":6993.7,"ask":6994.0},{"a":"hfm_premium","s":5.0,"bid":6997.87,"ask":6998.37},{"a":"three_pure","s":5.0,"bid":6993.6,"ask":6994.1},{"a":"exness_pro","s":5.0,"bid":6997.38,"ask":6997.88},{"a":"xm_kiwami","s":5.5,"bid":6991.37,"ask":6991.92},{"a":"vantage_std","s":6.0,"bid":6998.88,"ask":6999.48},{"a":"axiory_std","s":6.8,"bid":6993.07,"ask":6993.75},{"a":"exness_std","s":7.2,"bid":6996.74,"ask":6997.46},{"a":"titan_blade","s":8.0,"bid":6995.8,"ask":6996.6},{"a":"xs_std","s":11.0,"bid":6990.6,"ask":6991.7},{"a":"titan_std","s":20.0,"bid":6994.9,"ask":6996.9},{"a":"fxgt_std","s":53.2,"bid":6989.94,"ask":6995.26}],"US100":[{"a":"icm_std","s":0.9,"bid":26009.5,"ask":26010.4},{"a":"titan_blade","s":1.0,"bid":26023.1,"ask":26024.1},{"a":"exness_pro","s":1.5,"bid":26030.56,"ask":26032.07},{"a":"vantage_std","s":1.8,"bid":26037.11,"ask":26038.91},{"a":"axiory_std","s":1.9,"bid":26008.81,"ask":26010.71},{"a":"xs_std","s":1.9,"bid":25997.35,"ask":25999.25},{"a":"xm_kiwami","s":2.0,"bid":26000.1,"ask":26002.05},{"a":"three_pure","s":2.0,"bid":26009.0,"ask":26011.0},{"a":"hfm_premium","s":2.1,"bid":26013.1,"ask":26015.2},{"a":"exness_std","s":2.2,"bid":26030.18,"ask":26032.34},{"a":"titan_std","s":2.2,"bid":26019.0,"ask":26021.2},{"a":"axi_std","s":2.5,"bid":26159.75,"ask":26162.25},{"a":"fxgt_std","s":3.4,"bid":26003.3,"ask":26006.7}],"JP225":[{"a":"icm_std","s":4.0,"bid":58297.0,"ask":58301.0},{"a":"exness_pro","s":4.2,"bid":58327.3,"ask":58331.5},{"a":"xm_kiwami","s":6.0,"bid":58295.0,"ask":58301.0},{"a":"exness_std","s":6.0,"bid":58331.5,"ask":58337.5},{"a":"titan_blade","s":8.0,"bid":58311.7,"ask":58319.7},{"a":"titan_std","s":9.2,"bid":58306.1,"ask":58315.3},{"a":"xs_std","s":10.0,"bid":58289.0,"ask":58299.0},{"a":"vantage_std","s":11.0,"bid":58324.4,"ask":58335.4},{"a":"axiory_std","s":11.0,"bid":58305.17,"ask":58316.17},{"a":"fxgt_std","s":12.0,"bid":58296.0,"ask":58308.0},{"a":"hfm_premium","s":16.0,"bid":58322.0,"ask":58338.0},{"a":"three_pure","s":16.0,"bid":58301.0,"ask":58317.0},{"a":"axi_std","s":18.0,"bid":58299.5,"ask":58317.5}],"CRUDE":[{"a":"exness_pro","s":1.4,"bid":89.151,"ask":89.165},{"a":"exness_std","s":2.0,"bid":89.049,"ask":89.069},{"a":"icm_std","s":2.0,"bid":92.14,"ask":92.16},{"a":"axi_std","s":2.5,"bid":89.143,"ask":89.168},{"a":"xm_kiwami","s":3.0,"bid":92.24,"ask":92.27},{"a":"xs_std","s":3.8,"bid":92.234,"ask":92.272},{"a":"titan_blade","s":6.0,"bid":92.32,"ask":92.38},{"a":"titan_std","s":7.0,"bid":92.15,"ask":92.22},{"a":"vantage_std","s":7.3,"bid":92.092,"ask":92.165},{"a":"axiory_std","s":7.6,"bid":92.234,"ask":92.31},{"a":"three_pure","s":9.0,"bid":92.3,"ask":92.39},{"a":"hfm_premium","s":12.0,"bid":92.23,"ask":92.35},{"a":"fxgt_std","s":19.0,"bid":92.05,"ask":92.24}],"NGAS":[{"a":"icm_std","s":5.0,"bid":2.617,"ask":2.622},{"a":"exness_pro","s":6.7,"bid":2.7336,"ask":2.7403},{"a":"vantage_std","s":7.0,"bid":2.641,"ask":2.648},{"a":"exness_std","s":9.5,"bid":2.7327,"ask":2.7422},{"a":"axiory_std","s":10.0,"bid":2.733,"ask":2.743},{"a":"xm_kiwami","s":11.0,"bid":2.636,"ask":2.647},{"a":"axi_std","s":11.0,"bid":2.61,"ask":2.621},{"a":"titan_blade","s":20.0,"bid":2.61,"ask":2.63},{"a":"titan_std","s":22.0,"bid":2.609,"ask":2.631},{"a":"xs_std","s":25.0,"bid":2.726,"ask":2.751},{"a":"fxgt_std","s":63.0,"bid":2.71,"ask":2.773}]}}