{"updated_at":"2026-04-17T14:28:51Z","data":{"USDJPY":[{"a":"titan_blade","s":0.2,"bid":157.88,"ask":157.882},{"a":"exness_pro","s":0.7,"bid":157.861,"ask":157.868},{"a":"axi_std","s":0.8,"bid":157.9,"ask":157.908},{"a":"icm_std","s":0.9,"bid":157.851,"ask":157.86},{"a":"exness_std","s":1.0,"bid":157.851,"ask":157.861},{"a":"three_pure","s":1.1,"bid":157.837,"ask":157.848},{"a":"titan_std","s":1.1,"bid":157.885,"ask":157.896},{"a":"xs_std","s":1.2,"bid":157.837,"ask":157.849},{"a":"xm_kiwami","s":1.3,"bid":157.873,"ask":157.886},{"a":"axiory_std","s":1.6,"bid":157.901,"ask":157.917},{"a":"vantage_std","s":2.1,"bid":157.857,"ask":157.878},{"a":"xm_std","s":2.5,"bid":157.867,"ask":157.892},{"a":"fxgt_std","s":2.5,"bid":157.855,"ask":157.88},{"a":"hfm_premium","s":3.0,"bid":157.838,"ask":157.868}],"EURUSD":[{"a":"titan_blade","s":0.1,"bid":1.18306,"ask":1.18307},{"a":"exness_pro","s":0.6,"bid":1.18313,"ask":1.18319},{"a":"axi_std","s":0.7,"bid":1.18292,"ask":1.18299},{"a":"exness_std","s":0.8,"bid":1.18299,"ask":1.18307},{"a":"three_pure","s":0.8,"bid":1.18295,"ask":1.18303},{"a":"xm_kiwami","s":0.9,"bid":1.18308,"ask":1.18317},{"a":"icm_std","s":0.9,"bid":1.18301,"ask":1.1831},{"a":"xs_std","s":1.0,"bid":1.18306,"ask":1.18316},{"a":"titan_std","s":1.0,"bid":1.18293,"ask":1.18303},{"a":"vantage_std","s":1.4,"bid":1.18296,"ask":1.1831},{"a":"axiory_std","s":1.4,"bid":1.18284,"ask":1.18298},{"a":"xm_std","s":1.8,"bid":1.18304,"ask":1.18322},{"a":"fxgt_std","s":1.9,"bid":1.18292,"ask":1.18311},{"a":"hfm_premium","s":1.9,"bid":1.18303,"ask":1.18322}],"GBPUSD":[{"a":"titan_blade","s":0.2,"bid":1.35872,"ask":1.35874},{"a":"exness_pro","s":0.7,"bid":1.35876,"ask":1.35883},{"a":"three_pure","s":0.8,"bid":1.35862,"ask":1.3587},{"a":"axi_std","s":0.8,"bid":1.3586,"ask":1.35868},{"a":"xm_kiwami","s":0.9,"bid":1.35873,"ask":1.35882},{"a":"icm_std","s":0.9,"bid":1.35862,"ask":1.35871},{"a":"exness_std","s":1.0,"bid":1.35858,"ask":1.35868},{"a":"xs_std","s":1.1,"bid":1.35871,"ask":1.35882},{"a":"titan_std","s":1.1,"bid":1.35861,"ask":1.35872},{"a":"vantage_std","s":1.8,"bid":1.35858,"ask":1.35876},{"a":"axiory_std","s":1.8,"bid":1.35854,"ask":1.35872},{"a":"fxgt_std","s":1.9,"bid":1.35857,"ask":1.35876},{"a":"xm_std","s":2.0,"bid":1.35867,"ask":1.35887},{"a":"hfm_premium","s":2.3,"bid":1.35861,"ask":1.35884}],"AUDUSD":[{"a":"titan_blade","s":0.2,"bid":0.72118,"ask":0.7212},{"a":"exness_pro","s":0.6,"bid":0.72121,"ask":0.72127},{"a":"axi_std","s":0.7,"bid":0.72114,"ask":0.72121},{"a":"three_pure","s":0.8,"bid":0.72116,"ask":0.72124},{"a":"exness_std","s":0.9,"bid":0.7211,"ask":0.72119},{"a":"icm_std","s":0.9,"bid":0.72111,"ask":0.7212},{"a":"titan_std","s":1.0,"bid":0.72112,"ask":0.72122},{"a":"xs_std","s":1.1,"bid":0.72115,"ask":0.72126},{"a":"xm_kiwami","s":1.3,"bid":0.72114,"ask":0.72127},{"a":"axiory_std","s":1.6,"bid":0.72105,"ask":0.72121},{"a":"hfm_premium","s":1.7,"bid":0.72121,"ask":0.72138},{"a":"vantage_std","s":2.1,"bid":0.72115,"ask":0.72136},{"a":"xm_std","s":2.3,"bid":0.72109,"ask":0.72132},{"a":"fxgt_std","s":2.4,"bid":0.72111,"ask":0.72135}],"USDCHF":[{"a":"titan_blade","s":0.0,"bid":0.7777,"ask":0.7777},{"a":"three_pure","s":0.7,"bid":0.77787,"ask":0.77794},{"a":"axi_std","s":0.8,"bid":0.778,"ask":0.77808},{"a":"icm_std","s":0.8,"bid":0.77766,"ask":0.77774},{"a":"exness_pro","s":0.9,"bid":0.77753,"ask":0.77762},{"a":"xs_std","s":1.0,"bid":0.7776,"ask":0.7777},{"a":"titan_std","s":1.0,"bid":0.7778,"ask":0.7779},{"a":"xm_kiwami","s":1.1,"bid":0.77756,"ask":0.77767},{"a":"exness_std","s":1.3,"bid":0.77766,"ask":0.77779},{"a":"vantage_std","s":1.9,"bid":0.77764,"ask":0.77783},{"a":"axiory_std","s":1.9,"bid":0.77792,"ask":0.77811},{"a":"fxgt_std","s":1.9,"bid":0.77762,"ask":0.77781},{"a":"hfm_premium","s":1.9,"bid":0.77754,"ask":0.77773},{"a":"xm_std","s":2.2,"bid":0.7775,"ask":0.77772}],"USDCAD":[{"a":"titan_blade","s":0.4,"bid":1.3653,"ask":1.36534},{"a":"three_pure","s":0.8,"bid":1.36529,"ask":1.36537},{"a":"axi_std","s":0.8,"bid":1.36528,"ask":1.36536},{"a":"icm_std","s":0.9,"bid":1.36522,"ask":1.36531},{"a":"exness_pro","s":1.0,"bid":1.36522,"ask":1.36532},{"a":"exness_std","s":1.4,"bid":1.3652,"ask":1.36534},{"a":"titan_std","s":1.4,"bid":1.3653,"ask":1.36544},{"a":"xs_std","s":1.5,"bid":1.36518,"ask":1.36533},{"a":"axiory_std","s":1.7,"bid":1.36523,"ask":1.3654},{"a":"xm_kiwami","s":1.9,"bid":1.36517,"ask":1.36536},{"a":"vantage_std","s":2.2,"bid":1.36511,"ask":1.36533},{"a":"xm_std","s":2.4,"bid":1.36514,"ask":1.36538},{"a":"hfm_premium","s":2.4,"bid":1.36524,"ask":1.36548},{"a":"fxgt_std","s":2.9,"bid":1.36506,"ask":1.36535}],"EURJPY":[{"a":"titan_blade","s":0.1,"bid":186.785,"ask":186.786},{"a":"axi_std","s":0.8,"bid":186.785,"ask":186.793},{"a":"three_pure","s":0.9,"bid":186.723,"ask":186.732},{"a":"titan_std","s":1.1,"bid":186.775,"ask":186.786},{"a":"icm_std","s":1.1,"bid":186.746,"ask":186.757},{"a":"exness_pro","s":1.1,"bid":186.775,"ask":186.786},{"a":"xs_std","s":1.4,"bid":186.742,"ask":186.756},{"a":"exness_std","s":1.6,"bid":186.744,"ask":186.76},{"a":"axiory_std","s":1.6,"bid":186.786,"ask":186.802},{"a":"xm_kiwami","s":2.2,"bid":186.782,"ask":186.804},{"a":"hfm_premium","s":2.2,"bid":186.748,"ask":186.77},{"a":"vantage_std","s":3.0,"bid":186.748,"ask":186.778},{"a":"fxgt_std","s":3.3,"bid":186.742,"ask":186.775}],"GBPJPY":[{"a":"three_pure","s":1.4,"bid":214.447,"ask":214.461},{"a":"icm_std","s":1.4,"bid":214.465,"ask":214.479},{"a":"axi_std","s":1.5,"bid":214.522,"ask":214.537},{"a":"titan_blade","s":1.8,"bid":214.508,"ask":214.526},{"a":"exness_pro","s":1.9,"bid":214.501,"ask":214.52},{"a":"xs_std","s":2.1,"bid":214.463,"ask":214.484},{"a":"xm_kiwami","s":2.2,"bid":214.511,"ask":214.533},{"a":"axiory_std","s":2.2,"bid":214.521,"ask":214.543},{"a":"titan_std","s":2.2,"bid":214.509,"ask":214.531},{"a":"exness_std","s":2.7,"bid":214.458,"ask":214.485},{"a":"fxgt_std","s":3.2,"bid":214.47,"ask":214.502},{"a":"hfm_premium","s":4.0,"bid":214.462,"ask":214.502},{"a":"vantage_std","s":5.2,"bid":214.458,"ask":214.51}],"AUDJPY":[{"a":"titan_blade","s":0.6,"bid":113.858,"ask":113.864},{"a":"three_pure","s":0.9,"bid":113.831,"ask":113.84},{"a":"axi_std","s":1.1,"bid":113.873,"ask":113.884},{"a":"icm_std","s":1.3,"bid":113.832,"ask":113.845},{"a":"exness_pro","s":1.3,"bid":113.854,"ask":113.867},{"a":"titan_std","s":1.5,"bid":113.858,"ask":113.873},{"a":"exness_std","s":1.9,"bid":113.829,"ask":113.848},{"a":"axiory_std","s":1.9,"bid":113.867,"ask":113.886},{"a":"xs_std","s":2.0,"bid":113.831,"ask":113.851},{"a":"xm_kiwami","s":2.3,"bid":113.851,"ask":113.874},{"a":"vantage_std","s":2.9,"bid":113.85,"ask":113.879},{"a":"fxgt_std","s":3.3,"bid":113.843,"ask":113.876},{"a":"hfm_premium","s":3.5,"bid":113.841,"ask":113.876}],"XAUUSD":[{"a":"three_pure","s":1.5,"bid":4874.54,"ask":4874.69},{"a":"titan_std","s":1.5,"bid":4877.13,"ask":4877.28},{"a":"icm_std","s":1.5,"bid":4879.21,"ask":4879.36},{"a":"axi_std","s":1.6,"bid":4876.85,"ask":4877.01},{"a":"xs_std","s":2.0,"bid":4879.51,"ask":4879.71},{"a":"titan_blade","s":2.1,"bid":4878.5,"ask":4878.71},{"a":"exness_pro","s":2.5,"bid":4879.987,"ask":4880.239},{"a":"xm_kiwami","s":2.9,"bid":4879.74,"ask":4880.03},{"a":"hfm_premium","s":3.4,"bid":4876.47,"ask":4876.81},{"a":"exness_std","s":3.6,"bid":4879.52,"ask":4879.88},{"a":"fxgt_std","s":3.7,"bid":4878.96,"ask":4879.33},{"a":"vantage_std","s":4.2,"bid":4879.19,"ask":4879.61},{"a":"axiory_std","s":8.9,"bid":4877.26,"ask":4878.15}],"XAGUSD":[{"a":"exness_pro","s":21.0,"bid":82.651,"ask":82.672},{"a":"axi_std","s":29.0,"bid":82.591,"ask":82.62},{"a":"exness_std","s":30.0,"bid":82.6,"ask":82.63},{"a":"icm_std","s":30.0,"bid":82.612,"ask":82.642},{"a":"vantage_std","s":35.0,"bid":82.597,"ask":82.632},{"a":"xm_kiwami","s":52.0,"bid":82.631,"ask":82.683},{"a":"titan_std","s":57.0,"bid":82.586,"ask":82.643},{"a":"titan_blade","s":58.0,"bid":82.606,"ask":82.664},{"a":"xs_std","s":67.0,"bid":82.614,"ask":82.681},{"a":"hfm_premium","s":71.0,"bid":82.532,"ask":82.603},{"a":"axiory_std","s":79.0,"bid":82.599,"ask":82.678},{"a":"three_pure","s":79.0,"bid":82.49,"ask":82.569},{"a":"fxgt_std","s":80.0,"bid":82.566,"ask":82.646}],"BTCUSD":[{"a":"exness_pro","s":9.8,"bid":77664.5,"ask":77674.3},{"a":"axi_std","s":12.0,"bid":77582.72,"ask":77594.72},{"a":"icm_std","s":12.0,"bid":77682.15,"ask":77694.15},{"a":"exness_std","s":14.0,"bid":77692.72,"ask":77706.72},{"a":"three_pure","s":19.0,"bid":77652.0,"ask":77671.0},{"a":"xm_kiwami","s":22.5,"bid":77605.9,"ask":77628.4},{"a":"vantage_std","s":25.0,"bid":77664.13,"ask":77689.08},{"a":"xs_std","s":37.0,"bid":77658.53,"ask":77695.53},{"a":"titan_blade","s":37.9,"bid":77668.0,"ask":77705.9},{"a":"titan_std","s":38.0,"bid":77614.3,"ask":77652.3},{"a":"fxgt_std","s":45.1,"bid":77688.08,"ask":77733.22},{"a":"hfm_premium","s":62.0,"bid":77682.075,"ask":77744.075}],"ETHUSD":[{"a":"exness_pro","s":1.0,"bid":2439.27,"ask":2440.25},{"a":"axi_std","s":1.3,"bid":2437.03,"ask":2438.28},{"a":"exness_std","s":1.4,"bid":2438.24,"ask":2439.64},{"a":"three_pure","s":2.1,"bid":2434.7,"ask":2436.8},{"a":"vantage_std","s":2.5,"bid":2436.58,"ask":2439.04},{"a":"icm_std","s":2.9,"bid":2437.26,"ask":2440.16},{"a":"xm_kiwami","s":3.5,"bid":2436.96,"ask":2440.41},{"a":"fxgt_std","s":3.9,"bid":2435.86,"ask":2439.78},{"a":"xs_std","s":4.6,"bid":2435.61,"ask":2440.21},{"a":"hfm_premium","s":4.9,"bid":2436.345,"ask":2441.205},{"a":"titan_std","s":7.5,"bid":2434.7,"ask":2442.18},{"a":"titan_blade","s":7.5,"bid":2435.9,"ask":2443.35}],"US30":[{"a":"icm_std","s":0.7,"bid":49536.5,"ask":49537.2},{"a":"axi_std","s":0.8,"bid":49518.45,"ask":49519.25},{"a":"exness_pro","s":1.5,"bid":49575.7,"ask":49577.2},{"a":"xs_std","s":2.0,"bid":49549.8,"ask":49551.8},{"a":"three_pure","s":2.0,"bid":49543.0,"ask":49545.0},{"a":"titan_blade","s":2.0,"bid":49551.3,"ask":49553.3},{"a":"exness_std","s":2.1,"bid":49559.1,"ask":49561.2},{"a":"vantage_std","s":3.1,"bid":49564.48,"ask":49567.58},{"a":"titan_std","s":3.2,"bid":49550.7,"ask":49553.9},{"a":"xm_kiwami","s":3.9,"bid":49542.05,"ask":49545.95},{"a":"axiory_std","s":4.2,"bid":49537.76,"ask":49541.96},{"a":"fxgt_std","s":4.7,"bid":49536.44,"ask":49541.16},{"a":"hfm_premium","s":6.8,"bid":49713.91,"ask":49720.72}],"US500":[{"a":"axi_std","s":3.0,"bid":7115.2,"ask":7115.5},{"a":"icm_std","s":3.0,"bid":7116.5,"ask":7116.8},{"a":"hfm_premium","s":5.0,"bid":7124.4,"ask":7124.9},{"a":"three_pure","s":5.0,"bid":7119.8,"ask":7120.3},{"a":"exness_pro","s":5.0,"bid":7123.62,"ask":7124.12},{"a":"xm_kiwami","s":5.5,"bid":7117.36,"ask":7117.91},{"a":"vantage_std","s":6.0,"bid":7122.53,"ask":7123.13},{"a":"axiory_std","s":6.8,"bid":7117.52,"ask":7118.2},{"a":"exness_std","s":7.2,"bid":7122.43,"ask":7123.15},{"a":"titan_blade","s":8.0,"bid":7119.2,"ask":7120.0},{"a":"xs_std","s":12.0,"bid":7117.3,"ask":7118.5},{"a":"titan_std","s":20.0,"bid":7119.1,"ask":7121.1},{"a":"fxgt_std","s":54.2,"bid":7113.64,"ask":7119.06}],"US100":[{"a":"icm_std","s":0.9,"bid":26582.2,"ask":26583.1},{"a":"titan_blade","s":1.0,"bid":26591.5,"ask":26592.5},{"a":"exness_pro","s":1.5,"bid":26610.07,"ask":26611.58},{"a":"axiory_std","s":1.9,"bid":26582.93,"ask":26584.83},{"a":"xs_std","s":1.9,"bid":26584.95,"ask":26586.85},{"a":"xm_kiwami","s":2.0,"bid":26587.52,"ask":26589.47},{"a":"three_pure","s":2.0,"bid":26594.0,"ask":26596.0},{"a":"hfm_premium","s":2.1,"bid":26598.0,"ask":26600.1},{"a":"titan_std","s":2.2,"bid":26595.6,"ask":26597.8},{"a":"exness_std","s":2.4,"bid":26604.75,"ask":26607.15},{"a":"axi_std","s":2.5,"bid":26730.25,"ask":26732.75},{"a":"fxgt_std","s":3.5,"bid":26575.13,"ask":26578.67},{"a":"vantage_std","s":5.5,"bid":26597.43,"ask":26602.89}],"JP225":[{"a":"icm_std","s":4.0,"bid":59763.0,"ask":59767.0},{"a":"exness_pro","s":4.5,"bid":59794.7,"ask":59799.2},{"a":"xm_kiwami","s":6.0,"bid":59750.0,"ask":59756.0},{"a":"exness_std","s":6.4,"bid":59789.7,"ask":59796.1},{"a":"titan_blade","s":8.0,"bid":59759.8,"ask":59767.8},{"a":"titan_std","s":9.2,"bid":59759.2,"ask":59768.4},{"a":"xs_std","s":10.0,"bid":59765.5,"ask":59775.5},{"a":"vantage_std","s":11.0,"bid":59801.4,"ask":59812.4},{"a":"axiory_std","s":11.0,"bid":59748.28,"ask":59759.28},{"a":"fxgt_std","s":12.0,"bid":59765.0,"ask":59777.0},{"a":"hfm_premium","s":16.0,"bid":59794.0,"ask":59810.0},{"a":"three_pure","s":16.0,"bid":59796.0,"ask":59812.0},{"a":"axi_std","s":18.0,"bid":59737.5,"ask":59755.5}],"CRUDE":[{"a":"exness_pro","s":1.4,"bid":80.522,"ask":80.536},{"a":"exness_std","s":2.0,"bid":80.76,"ask":80.78},{"a":"icm_std","s":2.0,"bid":83.83,"ask":83.85},{"a":"axi_std","s":2.5,"bid":80.709,"ask":80.734},{"a":"xm_kiwami","s":3.0,"bid":83.51,"ask":83.54},{"a":"xs_std","s":3.8,"bid":83.741,"ask":83.779},{"a":"titan_blade","s":6.0,"bid":83.66,"ask":83.72},{"a":"titan_std","s":7.0,"bid":83.64,"ask":83.71},{"a":"axiory_std","s":7.6,"bid":84.272,"ask":84.348},{"a":"three_pure","s":9.0,"bid":84.58,"ask":84.67},{"a":"vantage_std","s":10.8,"bid":83.729,"ask":83.837},{"a":"hfm_premium","s":12.0,"bid":80.77,"ask":80.89},{"a":"fxgt_std","s":19.0,"bid":83.69,"ask":83.88}],"NGAS":[{"a":"icm_std","s":5.0,"bid":2.658,"ask":2.663},{"a":"vantage_std","s":7.0,"bid":2.678,"ask":2.685},{"a":"exness_pro","s":7.0,"bid":2.778,"ask":2.785},{"a":"exness_std","s":9.9,"bid":2.7795,"ask":2.7894},{"a":"xm_kiwami","s":11.0,"bid":2.673,"ask":2.684},{"a":"axi_std","s":12.0,"bid":2.65,"ask":2.662},{"a":"axiory_std","s":15.0,"bid":2.775,"ask":2.79},{"a":"titan_blade","s":21.0,"bid":2.647,"ask":2.668},{"a":"titan_std","s":22.0,"bid":2.645,"ask":2.667},{"a":"xs_std","s":29.0,"bid":2.767,"ask":2.796},{"a":"fxgt_std","s":63.0,"bid":2.755,"ask":2.818}]}}