{"updated_at":"2026-04-20T07:23:49Z","data":{"USDJPY":[{"a":"titan_blade","s":0.1,"bid":158.752,"ask":158.753},{"a":"vantage_raw","s":0.4,"bid":158.756,"ask":158.76},{"a":"exness_pro","s":0.7,"bid":158.74,"ask":158.747},{"a":"axi_std","s":0.7,"bid":158.749,"ask":158.756},{"a":"icm_std","s":0.8,"bid":158.752,"ask":158.76},{"a":"three_pure","s":0.8,"bid":158.729,"ask":158.737},{"a":"xm_kiwami","s":1.0,"bid":158.726,"ask":158.736},{"a":"exness_std","s":1.0,"bid":158.725,"ask":158.735},{"a":"titan_std","s":1.1,"bid":158.741,"ask":158.752},{"a":"xs_std","s":1.1,"bid":158.727,"ask":158.738},{"a":"axiory_std","s":1.6,"bid":158.742,"ask":158.758},{"a":"fxgt_optimus","s":1.8,"bid":158.751,"ask":158.769},{"a":"vantage_std","s":2.1,"bid":158.722,"ask":158.743},{"a":"hfm_premium","s":2.2,"bid":158.724,"ask":158.746},{"a":"xm_std","s":2.3,"bid":158.753,"ask":158.776},{"a":"fxgt_std","s":2.5,"bid":158.722,"ask":158.747}],"EURUSD":[{"a":"vantage_raw","s":0.0,"bid":1.17697,"ask":1.17697},{"a":"titan_blade","s":0.1,"bid":1.17708,"ask":1.17709},{"a":"exness_pro","s":0.6,"bid":1.17709,"ask":1.17715},{"a":"three_pure","s":0.6,"bid":1.17713,"ask":1.17719},{"a":"axi_std","s":0.7,"bid":1.17704,"ask":1.17711},{"a":"icm_std","s":0.8,"bid":1.17696,"ask":1.17704},{"a":"exness_std","s":0.8,"bid":1.17706,"ask":1.17714},{"a":"xm_kiwami","s":0.9,"bid":1.17712,"ask":1.17721},{"a":"xs_std","s":1.0,"bid":1.17706,"ask":1.17716},{"a":"titan_std","s":1.1,"bid":1.17699,"ask":1.1771},{"a":"axiory_std","s":1.4,"bid":1.17691,"ask":1.17705},{"a":"vantage_std","s":1.4,"bid":1.17705,"ask":1.17719},{"a":"fxgt_optimus","s":1.5,"bid":1.17688,"ask":1.17703},{"a":"hfm_premium","s":1.6,"bid":1.17703,"ask":1.17719},{"a":"xm_std","s":1.8,"bid":1.17677,"ask":1.17695},{"a":"fxgt_std","s":1.9,"bid":1.17701,"ask":1.1772}],"GBPUSD":[{"a":"vantage_raw","s":0.1,"bid":1.35157,"ask":1.35158},{"a":"titan_blade","s":0.4,"bid":1.35165,"ask":1.35169},{"a":"exness_pro","s":0.7,"bid":1.35165,"ask":1.35172},{"a":"axi_std","s":0.8,"bid":1.35155,"ask":1.35163},{"a":"three_pure","s":0.8,"bid":1.35161,"ask":1.35169},{"a":"icm_std","s":1.0,"bid":1.35153,"ask":1.35163},{"a":"xm_kiwami","s":1.0,"bid":1.35163,"ask":1.35173},{"a":"exness_std","s":1.0,"bid":1.3516,"ask":1.3517},{"a":"titan_std","s":1.2,"bid":1.35157,"ask":1.35169},{"a":"xs_std","s":1.2,"bid":1.3516,"ask":1.35172},{"a":"axiory_std","s":1.6,"bid":1.35148,"ask":1.35164},{"a":"fxgt_optimus","s":1.7,"bid":1.35149,"ask":1.35166},{"a":"vantage_std","s":1.9,"bid":1.35158,"ask":1.35177},{"a":"fxgt_std","s":1.9,"bid":1.35157,"ask":1.35176},{"a":"hfm_premium","s":2.4,"bid":1.35153,"ask":1.35177},{"a":"xm_std","s":2.4,"bid":1.35134,"ask":1.35158}],"AUDUSD":[{"a":"vantage_raw","s":0.2,"bid":0.71613,"ask":0.71615},{"a":"titan_blade","s":0.2,"bid":0.71641,"ask":0.71643},{"a":"exness_pro","s":0.6,"bid":0.71638,"ask":0.71644},{"a":"axi_std","s":0.7,"bid":0.71633,"ask":0.7164},{"a":"three_pure","s":0.8,"bid":0.71637,"ask":0.71645},{"a":"icm_std","s":0.9,"bid":0.71632,"ask":0.71641},{"a":"exness_std","s":0.9,"bid":0.71638,"ask":0.71647},{"a":"titan_std","s":1.0,"bid":0.7163,"ask":0.7164},{"a":"xs_std","s":1.1,"bid":0.71635,"ask":0.71646},{"a":"xm_kiwami","s":1.3,"bid":0.71638,"ask":0.71651},{"a":"axiory_std","s":1.6,"bid":0.71624,"ask":0.7164},{"a":"fxgt_optimus","s":1.6,"bid":0.71606,"ask":0.71622},{"a":"hfm_premium","s":1.7,"bid":0.71632,"ask":0.71649},{"a":"vantage_std","s":2.1,"bid":0.71632,"ask":0.71653},{"a":"fxgt_std","s":2.1,"bid":0.7163,"ask":0.71651},{"a":"xm_std","s":2.3,"bid":0.71595,"ask":0.71618}],"USDCHF":[{"a":"titan_blade","s":0.0,"bid":0.78152,"ask":0.78152},{"a":"vantage_raw","s":0.1,"bid":0.78173,"ask":0.78174},{"a":"three_pure","s":0.7,"bid":0.78141,"ask":0.78148},{"a":"axi_std","s":0.8,"bid":0.78139,"ask":0.78147},{"a":"icm_std","s":0.9,"bid":0.7815,"ask":0.78159},{"a":"exness_pro","s":0.9,"bid":0.78138,"ask":0.78147},{"a":"titan_std","s":1.0,"bid":0.78145,"ask":0.78155},{"a":"xm_kiwami","s":1.1,"bid":0.78136,"ask":0.78147},{"a":"xs_std","s":1.2,"bid":0.78137,"ask":0.78149},{"a":"exness_std","s":1.3,"bid":0.78136,"ask":0.78149},{"a":"vantage_std","s":1.9,"bid":0.78134,"ask":0.78153},{"a":"fxgt_optimus","s":1.9,"bid":0.78164,"ask":0.78183},{"a":"fxgt_std","s":1.9,"bid":0.78133,"ask":0.78152},{"a":"axiory_std","s":2.0,"bid":0.78142,"ask":0.78162},{"a":"xm_std","s":2.0,"bid":0.78167,"ask":0.78187},{"a":"hfm_premium","s":2.1,"bid":0.7814,"ask":0.78161}],"USDCAD":[{"a":"vantage_raw","s":0.0,"bid":1.36907,"ask":1.36907},{"a":"titan_blade","s":0.2,"bid":1.36892,"ask":1.36894},{"a":"three_pure","s":0.7,"bid":1.36889,"ask":1.36896},{"a":"axi_std","s":0.8,"bid":1.36887,"ask":1.36895},{"a":"icm_std","s":1.0,"bid":1.36891,"ask":1.36901},{"a":"exness_pro","s":1.0,"bid":1.36888,"ask":1.36898},{"a":"titan_std","s":1.2,"bid":1.36887,"ask":1.36899},{"a":"exness_std","s":1.4,"bid":1.36887,"ask":1.36901},{"a":"xs_std","s":1.6,"bid":1.36885,"ask":1.36901},{"a":"fxgt_optimus","s":1.7,"bid":1.36899,"ask":1.36916},{"a":"axiory_std","s":2.0,"bid":1.36891,"ask":1.36911},{"a":"xm_kiwami","s":2.0,"bid":1.36883,"ask":1.36903},{"a":"vantage_std","s":2.1,"bid":1.36884,"ask":1.36905},{"a":"hfm_premium","s":2.1,"bid":1.36883,"ask":1.36904},{"a":"fxgt_std","s":2.7,"bid":1.36881,"ask":1.36908},{"a":"xm_std","s":2.7,"bid":1.36894,"ask":1.36921}],"EURJPY":[{"a":"titan_blade","s":0.2,"bid":186.864,"ask":186.866},{"a":"vantage_raw","s":0.4,"bid":186.849,"ask":186.853},{"a":"three_pure","s":0.8,"bid":186.851,"ask":186.859},{"a":"axi_std","s":0.9,"bid":186.858,"ask":186.867},{"a":"icm_std","s":1.1,"bid":186.851,"ask":186.862},{"a":"exness_pro","s":1.1,"bid":186.849,"ask":186.86},{"a":"titan_std","s":1.2,"bid":186.848,"ask":186.86},{"a":"xs_std","s":1.6,"bid":186.837,"ask":186.853},{"a":"exness_std","s":1.6,"bid":186.836,"ask":186.852},{"a":"axiory_std","s":1.8,"bid":186.842,"ask":186.86},{"a":"xm_kiwami","s":1.9,"bid":186.843,"ask":186.862},{"a":"hfm_premium","s":2.2,"bid":186.837,"ask":186.859},{"a":"fxgt_optimus","s":2.6,"bid":186.838,"ask":186.864},{"a":"xm_std","s":2.9,"bid":186.829,"ask":186.858},{"a":"fxgt_std","s":3.0,"bid":186.831,"ask":186.861},{"a":"vantage_std","s":3.5,"bid":186.828,"ask":186.863}],"GBPJPY":[{"a":"vantage_raw","s":1.0,"bid":214.565,"ask":214.575},{"a":"three_pure","s":1.1,"bid":214.553,"ask":214.564},{"a":"axi_std","s":1.3,"bid":214.56,"ask":214.573},{"a":"titan_blade","s":1.4,"bid":214.573,"ask":214.587},{"a":"icm_std","s":1.5,"bid":214.563,"ask":214.578},{"a":"xs_std","s":1.9,"bid":214.542,"ask":214.561},{"a":"exness_pro","s":1.9,"bid":214.564,"ask":214.583},{"a":"titan_std","s":2.0,"bid":214.555,"ask":214.575},{"a":"xm_kiwami","s":2.1,"bid":214.544,"ask":214.565},{"a":"axiory_std","s":2.2,"bid":214.569,"ask":214.591},{"a":"exness_std","s":2.2,"bid":214.538,"ask":214.56},{"a":"hfm_premium","s":3.0,"bid":214.541,"ask":214.571},{"a":"fxgt_optimus","s":3.1,"bid":214.557,"ask":214.588},{"a":"fxgt_std","s":3.2,"bid":214.54,"ask":214.572},{"a":"xm_std","s":3.3,"bid":214.547,"ask":214.58},{"a":"vantage_std","s":5.1,"bid":214.527,"ask":214.578}],"AUDJPY":[{"a":"titan_blade","s":0.2,"bid":113.733,"ask":113.735},{"a":"three_pure","s":0.5,"bid":113.719,"ask":113.724},{"a":"vantage_raw","s":0.5,"bid":113.689,"ask":113.694},{"a":"axi_std","s":1.1,"bid":113.721,"ask":113.732},{"a":"titan_std","s":1.2,"bid":113.712,"ask":113.724},{"a":"icm_std","s":1.3,"bid":113.721,"ask":113.734},{"a":"exness_pro","s":1.3,"bid":113.719,"ask":113.732},{"a":"xs_std","s":1.7,"bid":113.708,"ask":113.725},{"a":"axiory_std","s":1.9,"bid":113.718,"ask":113.737},{"a":"exness_std","s":1.9,"bid":113.711,"ask":113.73},{"a":"xm_kiwami","s":2.3,"bid":113.71,"ask":113.733},{"a":"fxgt_optimus","s":2.6,"bid":113.68,"ask":113.706},{"a":"hfm_premium","s":2.9,"bid":113.704,"ask":113.733},{"a":"vantage_std","s":3.1,"bid":113.703,"ask":113.734},{"a":"fxgt_std","s":3.1,"bid":113.703,"ask":113.734},{"a":"xm_std","s":3.4,"bid":113.668,"ask":113.702}],"XAUUSD":[{"a":"icm_std","s":1.5,"bid":4801.49,"ask":4801.64},{"a":"axi_std","s":1.5,"bid":4802.69,"ask":4802.84},{"a":"three_pure","s":1.5,"bid":4804.32,"ask":4804.47},{"a":"vantage_raw","s":1.6,"bid":4803.91,"ask":4804.07},{"a":"titan_blade","s":1.6,"bid":4802.18,"ask":4802.34},{"a":"titan_std","s":1.7,"bid":4802.49,"ask":4802.66},{"a":"xs_std","s":2.0,"bid":4805.58,"ask":4805.78},{"a":"exness_pro","s":2.0,"bid":4802.043,"ask":4802.239},{"a":"xm_kiwami","s":2.7,"bid":4804.73,"ask":4805.0},{"a":"fxgt_optimus","s":3.4,"bid":4803.93,"ask":4804.27},{"a":"hfm_premium","s":3.4,"bid":4804.41,"ask":4804.75},{"a":"exness_std","s":3.6,"bid":4804.28,"ask":4804.64},{"a":"fxgt_std","s":3.7,"bid":4805.38,"ask":4805.75},{"a":"vantage_std","s":4.3,"bid":4804.69,"ask":4805.12},{"a":"xm_std","s":4.7,"bid":4802.89,"ask":4803.36},{"a":"axiory_std","s":7.7,"bid":4800.87,"ask":4801.64}],"XAGUSD":[{"a":"exness_pro","s":21.0,"bid":80.003,"ask":80.024},{"a":"axi_std","s":28.0,"bid":79.962,"ask":79.99},{"a":"exness_std","s":30.0,"bid":80.019,"ask":80.049},{"a":"vantage_raw","s":31.0,"bid":79.914,"ask":79.945},{"a":"icm_std","s":34.0,"bid":79.952,"ask":79.986},{"a":"vantage_std","s":40.0,"bid":80.026,"ask":80.066},{"a":"xm_kiwami","s":47.0,"bid":80.023,"ask":80.07},{"a":"xs_std","s":55.0,"bid":80.037,"ask":80.092},{"a":"titan_std","s":64.0,"bid":79.962,"ask":80.026},{"a":"titan_blade","s":64.0,"bid":79.982,"ask":80.046},{"a":"xm_std","s":71.0,"bid":79.886,"ask":79.957},{"a":"fxgt_optimus","s":72.0,"bid":79.899,"ask":79.971},{"a":"hfm_premium","s":74.0,"bid":79.984,"ask":80.058},{"a":"axiory_std","s":77.0,"bid":79.913,"ask":79.99},{"a":"fxgt_std","s":80.0,"bid":80.009,"ask":80.089},{"a":"three_pure","s":83.0,"bid":79.98,"ask":80.063}],"BTCUSD":[{"a":"exness_pro","s":9.8,"bid":75386.99,"ask":75396.79},{"a":"icm_std","s":12.0,"bid":75334.13,"ask":75346.13},{"a":"axi_std","s":12.0,"bid":75276.59,"ask":75288.59},{"a":"exness_std","s":14.0,"bid":75264.35,"ask":75278.35},{"a":"three_pure","s":19.0,"bid":75318.0,"ask":75337.0},{"a":"xm_kiwami","s":22.5,"bid":75229.5,"ask":75252.0},{"a":"vantage_std","s":25.0,"bid":75204.86,"ask":75229.81},{"a":"vantage_raw","s":25.0,"bid":75010.12,"ask":75035.13},{"a":"xs_std","s":27.0,"bid":75268.43,"ask":75295.43},{"a":"fxgt_optimus","s":32.5,"bid":75023.4,"ask":75055.9},{"a":"fxgt_std","s":42.8,"bid":75246.66,"ask":75289.47},{"a":"titan_std","s":43.6,"bid":75321.2,"ask":75364.8},{"a":"titan_blade","s":43.7,"bid":75358.1,"ask":75401.8},{"a":"xm_std","s":50.0,"bid":74986.35,"ask":75036.35},{"a":"hfm_premium","s":62.0,"bid":75239.765,"ask":75301.765}],"ETHUSD":[{"a":"exness_pro","s":1.0,"bid":2315.11,"ask":2316.09},{"a":"axi_std","s":1.3,"bid":2311.93,"ask":2313.18},{"a":"exness_std","s":1.4,"bid":2308.29,"ask":2309.69},{"a":"three_pure","s":2.1,"bid":2312.6,"ask":2314.7},{"a":"vantage_std","s":2.5,"bid":2307.47,"ask":2310.01},{"a":"vantage_raw","s":2.5,"bid":2294.34,"ask":2296.82},{"a":"icm_std","s":2.9,"bid":2312.51,"ask":2315.41},{"a":"fxgt_optimus","s":3.0,"bid":2293.84,"ask":2296.8},{"a":"xm_kiwami","s":3.5,"bid":2306.58,"ask":2310.03},{"a":"fxgt_std","s":4.4,"bid":2307.52,"ask":2311.9},{"a":"xs_std","s":4.6,"bid":2309.02,"ask":2313.62},{"a":"hfm_premium","s":4.9,"bid":2309.085,"ask":2313.945},{"a":"xm_std","s":4.9,"bid":2292.89,"ask":2297.79},{"a":"titan_std","s":7.5,"bid":2310.3,"ask":2317.8},{"a":"titan_blade","s":7.5,"bid":2311.7,"ask":2319.2}],"US30":[{"a":"axi_std","s":1.0,"bid":49155.35,"ask":49156.35},{"a":"icm_std","s":1.2,"bid":49153.3,"ask":49154.5},{"a":"exness_pro","s":1.5,"bid":49208.5,"ask":49210.0},{"a":"xs_std","s":2.0,"bid":49166.85,"ask":49168.85},{"a":"exness_std","s":2.1,"bid":49215.3,"ask":49217.4},{"a":"titan_blade","s":2.5,"bid":49197.5,"ask":49200.0},{"a":"three_pure","s":3.0,"bid":49202.0,"ask":49205.0},{"a":"fxgt_optimus","s":3.3,"bid":49150.19,"ask":49153.51},{"a":"titan_std","s":3.7,"bid":49194.6,"ask":49198.3},{"a":"vantage_std","s":3.7,"bid":49212.14,"ask":49215.86},{"a":"vantage_raw","s":3.7,"bid":49198.14,"ask":49201.86},{"a":"xm_kiwami","s":3.9,"bid":49164.05,"ask":49167.95},{"a":"fxgt_std","s":4.5,"bid":49163.63,"ask":49168.13},{"a":"axiory_std","s":4.9,"bid":49191.56,"ask":49196.46},{"a":"xm_std","s":5.5,"bid":49140.75,"ask":49146.25},{"a":"hfm_premium","s":6.8,"bid":49361.37,"ask":49368.18}],"US500":[{"a":"axi_std","s":3.0,"bid":7091.9,"ask":7092.2},{"a":"icm_std","s":5.0,"bid":7091.5,"ask":7092.0},{"a":"exness_pro","s":5.0,"bid":7100.92,"ask":7101.42},{"a":"three_pure","s":5.0,"bid":7098.8,"ask":7099.3},{"a":"hfm_premium","s":5.0,"bid":7104.17,"ask":7104.67},{"a":"xm_kiwami","s":5.5,"bid":7093.81,"ask":7094.36},{"a":"vantage_std","s":6.0,"bid":7101.83,"ask":7102.43},{"a":"vantage_raw","s":6.0,"bid":7099.33,"ask":7099.93},{"a":"axiory_std","s":7.0,"bid":7096.72,"ask":7097.42},{"a":"xm_std","s":7.0,"bid":7089.73,"ask":7090.43},{"a":"exness_std","s":7.2,"bid":7102.31,"ask":7103.03},{"a":"titan_blade","s":8.0,"bid":7097.4,"ask":7098.2},{"a":"xs_std","s":13.0,"bid":7093.1,"ask":7094.4},{"a":"titan_std","s":20.0,"bid":7096.8,"ask":7098.8},{"a":"fxgt_optimus","s":24.2,"bid":7089.64,"ask":7092.06},{"a":"fxgt_std","s":57.8,"bid":7090.46,"ask":7096.24}],"US100":[{"a":"icm_std","s":1.0,"bid":26551.2,"ask":26552.2},{"a":"titan_blade","s":1.0,"bid":26574.3,"ask":26575.3},{"a":"exness_pro","s":1.7,"bid":26587.79,"ask":26589.47},{"a":"vantage_std","s":1.8,"bid":26594.05,"ask":26595.85},{"a":"vantage_raw","s":1.8,"bid":26579.05,"ask":26580.85},{"a":"xs_std","s":1.9,"bid":26560.4,"ask":26562.3},{"a":"xm_kiwami","s":2.0,"bid":26562.4,"ask":26564.35},{"a":"three_pure","s":2.0,"bid":26581.0,"ask":26583.0},{"a":"axiory_std","s":2.1,"bid":26571.53,"ask":26573.63},{"a":"titan_std","s":2.2,"bid":26575.0,"ask":26577.2},{"a":"exness_std","s":2.4,"bid":26596.13,"ask":26598.53},{"a":"hfm_premium","s":2.4,"bid":26583.95,"ask":26586.35},{"a":"axi_std","s":2.5,"bid":26712.0,"ask":26714.5},{"a":"xm_std","s":2.6,"bid":26539.7,"ask":26542.3},{"a":"fxgt_optimus","s":3.0,"bid":26543.7,"ask":26546.65},{"a":"fxgt_std","s":3.4,"bid":26558.16,"ask":26561.56}],"JP225":[{"a":"icm_std","s":5.0,"bid":58880.0,"ask":58885.0},{"a":"exness_pro","s":5.0,"bid":58922.4,"ask":58927.4},{"a":"xm_kiwami","s":6.0,"bid":58906.0,"ask":58912.0},{"a":"exness_std","s":7.1,"bid":58941.5,"ask":58948.6},{"a":"xm_std","s":8.0,"bid":58890.0,"ask":58898.0},{"a":"titan_blade","s":8.0,"bid":58904.5,"ask":58912.5},{"a":"titan_std","s":9.2,"bid":58898.9,"ask":58908.1},{"a":"xs_std","s":10.0,"bid":58892.0,"ask":58902.0},{"a":"axiory_std","s":11.0,"bid":58895.51,"ask":58906.51},{"a":"vantage_std","s":11.0,"bid":58924.5,"ask":58935.5},{"a":"fxgt_optimus","s":12.0,"bid":58891.0,"ask":58903.0},{"a":"fxgt_std","s":14.0,"bid":58888.0,"ask":58902.0},{"a":"three_pure","s":16.0,"bid":58904.0,"ask":58920.0},{"a":"hfm_premium","s":16.0,"bid":58922.0,"ask":58938.0},{"a":"vantage_raw","s":16.0,"bid":58924.5,"ask":58940.5},{"a":"axi_std","s":18.0,"bid":58876.75,"ask":58894.75}],"CRUDE":[{"a":"exness_pro","s":1.4,"bid":86.53,"ask":86.544},{"a":"icm_std","s":2.0,"bid":89.55,"ask":89.57},{"a":"exness_std","s":2.0,"bid":86.456,"ask":86.476},{"a":"axi_std","s":2.5,"bid":86.532,"ask":86.557},{"a":"xm_kiwami","s":3.0,"bid":89.58,"ask":89.61},{"a":"xs_std","s":3.8,"bid":89.455,"ask":89.493},{"a":"xm_std","s":5.0,"bid":89.75,"ask":89.8},{"a":"titan_blade","s":6.0,"bid":89.52,"ask":89.58},{"a":"vantage_raw","s":6.7,"bid":89.516,"ask":89.583},{"a":"titan_std","s":7.0,"bid":89.49,"ask":89.56},{"a":"vantage_std","s":7.3,"bid":89.428,"ask":89.501},{"a":"axiory_std","s":7.6,"bid":90.439,"ask":90.515},{"a":"three_pure","s":11.0,"bid":90.38,"ask":90.49},{"a":"hfm_premium","s":13.0,"bid":86.79,"ask":86.92},{"a":"fxgt_optimus","s":16.0,"bid":89.47,"ask":89.63},{"a":"fxgt_std","s":20.0,"bid":89.37,"ask":89.57}],"NGAS":[{"a":"icm_std","s":3.0,"bid":2.717,"ask":2.72},{"a":"exness_pro","s":9.4,"bid":2.842,"ask":2.8514},{"a":"axi_std","s":11.0,"bid":2.849,"ask":2.86},{"a":"vantage_std","s":12.0,"bid":2.729,"ask":2.741},{"a":"vantage_raw","s":12.0,"bid":2.729,"ask":2.741},{"a":"exness_std","s":13.5,"bid":2.8394,"ask":2.8529},{"a":"xm_kiwami","s":16.0,"bid":2.726,"ask":2.742},{"a":"titan_blade","s":19.0,"bid":2.71,"ask":2.729},{"a":"titan_std","s":20.0,"bid":2.708,"ask":2.728},{"a":"xm_std","s":21.0,"bid":2.724,"ask":2.745},{"a":"axiory_std","s":30.0,"bid":2.833,"ask":2.863},{"a":"fxgt_optimus","s":38.0,"bid":2.828,"ask":2.866},{"a":"xs_std","s":42.0,"bid":2.825,"ask":2.867},{"a":"fxgt_std","s":67.0,"bid":2.813,"ask":2.88}]}}