{"updated_at":"2026-04-15T23:18:50Z","data":{"USDJPY":[{"a":"titan_blade","s":0.1,"bid":158.812,"ask":158.813},{"a":"axi_std","s":0.7,"bid":158.825,"ask":158.832},{"a":"exness_pro","s":0.7,"bid":158.814,"ask":158.821},{"a":"three_pure","s":0.8,"bid":158.827,"ask":158.835},{"a":"icm_std","s":0.9,"bid":158.81,"ask":158.819},{"a":"exness_std","s":1.0,"bid":158.811,"ask":158.821},{"a":"titan_std","s":1.1,"bid":158.809,"ask":158.82},{"a":"xm_kiwami","s":1.4,"bid":158.809,"ask":158.823},{"a":"xs_std","s":1.4,"bid":158.824,"ask":158.838},{"a":"axiory_std","s":1.9,"bid":158.817,"ask":158.836},{"a":"vantage_std","s":2.0,"bid":158.801,"ask":158.821},{"a":"hfm_premium","s":2.2,"bid":158.809,"ask":158.831},{"a":"fxgt_std","s":2.5,"bid":158.804,"ask":158.829},{"a":"xm_std","s":2.6,"bid":158.803,"ask":158.829}],"EURUSD":[{"a":"titan_blade","s":0.1,"bid":1.18045,"ask":1.18046},{"a":"three_pure","s":0.6,"bid":1.18038,"ask":1.18044},{"a":"axi_std","s":0.6,"bid":1.1804,"ask":1.18046},{"a":"exness_pro","s":0.6,"bid":1.1804,"ask":1.18046},{"a":"exness_std","s":0.8,"bid":1.18037,"ask":1.18045},{"a":"icm_std","s":0.9,"bid":1.18039,"ask":1.18048},{"a":"xm_kiwami","s":1.2,"bid":1.18037,"ask":1.18049},{"a":"titan_std","s":1.2,"bid":1.18039,"ask":1.18051},{"a":"axiory_std","s":1.3,"bid":1.18038,"ask":1.18051},{"a":"xs_std","s":1.3,"bid":1.18034,"ask":1.18047},{"a":"vantage_std","s":1.4,"bid":1.18041,"ask":1.18055},{"a":"hfm_premium","s":1.6,"bid":1.18034,"ask":1.1805},{"a":"fxgt_std","s":2.0,"bid":1.18032,"ask":1.18052},{"a":"xm_std","s":2.1,"bid":1.18033,"ask":1.18054}],"GBPUSD":[{"a":"titan_blade","s":0.1,"bid":1.35704,"ask":1.35705},{"a":"three_pure","s":0.7,"bid":1.35689,"ask":1.35696},{"a":"exness_pro","s":0.7,"bid":1.3569,"ask":1.35697},{"a":"axi_std","s":0.8,"bid":1.35692,"ask":1.357},{"a":"icm_std","s":0.9,"bid":1.35694,"ask":1.35703},{"a":"exness_std","s":1.0,"bid":1.35693,"ask":1.35703},{"a":"xs_std","s":1.4,"bid":1.35687,"ask":1.35701},{"a":"xm_kiwami","s":1.6,"bid":1.3569,"ask":1.35706},{"a":"vantage_std","s":1.8,"bid":1.35695,"ask":1.35713},{"a":"titan_std","s":1.8,"bid":1.3569,"ask":1.35708},{"a":"axiory_std","s":1.9,"bid":1.35697,"ask":1.35716},{"a":"fxgt_std","s":1.9,"bid":1.35689,"ask":1.35708},{"a":"hfm_premium","s":1.9,"bid":1.35687,"ask":1.35706},{"a":"xm_std","s":2.7,"bid":1.35684,"ask":1.35711}],"AUDUSD":[{"a":"titan_blade","s":0.1,"bid":0.71724,"ask":0.71725},{"a":"exness_pro","s":0.6,"bid":0.71716,"ask":0.71722},{"a":"axi_std","s":0.7,"bid":0.71714,"ask":0.71721},{"a":"three_pure","s":0.8,"bid":0.71716,"ask":0.71724},{"a":"exness_std","s":0.9,"bid":0.71713,"ask":0.71722},{"a":"icm_std","s":0.9,"bid":0.71717,"ask":0.71726},{"a":"xs_std","s":1.0,"bid":0.71715,"ask":0.71725},{"a":"titan_std","s":1.0,"bid":0.71719,"ask":0.71729},{"a":"xm_kiwami","s":1.3,"bid":0.71713,"ask":0.71726},{"a":"axiory_std","s":1.6,"bid":0.71709,"ask":0.71725},{"a":"hfm_premium","s":1.9,"bid":0.71711,"ask":0.7173},{"a":"vantage_std","s":2.1,"bid":0.71714,"ask":0.71735},{"a":"xm_std","s":2.3,"bid":0.71708,"ask":0.71731},{"a":"fxgt_std","s":2.3,"bid":0.71708,"ask":0.71731}],"USDCHF":[{"a":"titan_blade","s":0.0,"bid":0.78147,"ask":0.78147},{"a":"three_pure","s":0.8,"bid":0.78144,"ask":0.78152},{"a":"axi_std","s":0.8,"bid":0.78141,"ask":0.78149},{"a":"icm_std","s":0.8,"bid":0.78143,"ask":0.78151},{"a":"exness_pro","s":0.9,"bid":0.7814,"ask":0.78149},{"a":"xm_kiwami","s":1.1,"bid":0.78138,"ask":0.78149},{"a":"titan_std","s":1.2,"bid":0.78142,"ask":0.78154},{"a":"exness_std","s":1.3,"bid":0.78134,"ask":0.78147},{"a":"xs_std","s":1.3,"bid":0.7814,"ask":0.78153},{"a":"vantage_std","s":1.9,"bid":0.78136,"ask":0.78155},{"a":"axiory_std","s":1.9,"bid":0.78134,"ask":0.78153},{"a":"fxgt_std","s":2.0,"bid":0.78134,"ask":0.78154},{"a":"xm_std","s":2.2,"bid":0.78132,"ask":0.78154},{"a":"hfm_premium","s":2.3,"bid":0.78134,"ask":0.78157}],"USDCAD":[{"a":"titan_blade","s":0.3,"bid":1.3735,"ask":1.37353},{"a":"three_pure","s":0.8,"bid":1.37348,"ask":1.37356},{"a":"axi_std","s":0.8,"bid":1.3735,"ask":1.37358},{"a":"icm_std","s":1.0,"bid":1.37348,"ask":1.37358},{"a":"exness_pro","s":1.0,"bid":1.37346,"ask":1.37356},{"a":"exness_std","s":1.4,"bid":1.37344,"ask":1.37358},{"a":"xs_std","s":1.6,"bid":1.37344,"ask":1.3736},{"a":"titan_std","s":1.6,"bid":1.37342,"ask":1.37358},{"a":"xm_kiwami","s":2.2,"bid":1.3734,"ask":1.37362},{"a":"vantage_std","s":2.2,"bid":1.37341,"ask":1.37363},{"a":"axiory_std","s":2.2,"bid":1.37333,"ask":1.37355},{"a":"hfm_premium","s":2.3,"bid":1.3734,"ask":1.37363},{"a":"fxgt_std","s":2.7,"bid":1.37338,"ask":1.37365},{"a":"xm_std","s":3.0,"bid":1.37336,"ask":1.37366}],"EURJPY":[{"a":"titan_blade","s":0.3,"bid":187.472,"ask":187.475},{"a":"three_pure","s":0.9,"bid":187.478,"ask":187.487},{"a":"axi_std","s":1.1,"bid":187.475,"ask":187.486},{"a":"exness_pro","s":1.1,"bid":187.469,"ask":187.48},{"a":"titan_std","s":1.3,"bid":187.467,"ask":187.48},{"a":"icm_std","s":1.5,"bid":187.463,"ask":187.478},{"a":"exness_std","s":1.6,"bid":187.466,"ask":187.482},{"a":"axiory_std","s":1.8,"bid":187.471,"ask":187.489},{"a":"xs_std","s":1.9,"bid":187.474,"ask":187.493},{"a":"hfm_premium","s":2.3,"bid":187.462,"ask":187.485},{"a":"xm_kiwami","s":2.5,"bid":187.46,"ask":187.485},{"a":"vantage_std","s":3.0,"bid":187.454,"ask":187.484},{"a":"fxgt_std","s":3.5,"bid":187.453,"ask":187.488}],"GBPJPY":[{"a":"titan_blade","s":1.0,"bid":215.51,"ask":215.52},{"a":"three_pure","s":1.1,"bid":215.518,"ask":215.529},{"a":"axi_std","s":1.4,"bid":215.514,"ask":215.528},{"a":"icm_std","s":1.6,"bid":215.5,"ask":215.516},{"a":"exness_pro","s":1.9,"bid":215.503,"ask":215.522},{"a":"xs_std","s":2.3,"bid":215.511,"ask":215.534},{"a":"exness_std","s":2.7,"bid":215.498,"ask":215.525},{"a":"axiory_std","s":2.7,"bid":215.511,"ask":215.538},{"a":"hfm_premium","s":3.0,"bid":215.498,"ask":215.528},{"a":"titan_std","s":3.1,"bid":215.493,"ask":215.524},{"a":"fxgt_std","s":3.2,"bid":215.494,"ask":215.526},{"a":"xm_kiwami","s":3.3,"bid":215.493,"ask":215.526},{"a":"vantage_std","s":5.2,"bid":215.483,"ask":215.535}],"AUDJPY":[{"a":"titan_blade","s":0.6,"bid":113.904,"ask":113.91},{"a":"three_pure","s":0.9,"bid":113.908,"ask":113.917},{"a":"axi_std","s":1.1,"bid":113.911,"ask":113.922},{"a":"exness_pro","s":1.3,"bid":113.9,"ask":113.913},{"a":"icm_std","s":1.4,"bid":113.897,"ask":113.911},{"a":"axiory_std","s":1.6,"bid":113.898,"ask":113.914},{"a":"titan_std","s":1.6,"bid":113.902,"ask":113.918},{"a":"xs_std","s":1.7,"bid":113.905,"ask":113.922},{"a":"exness_std","s":1.9,"bid":113.899,"ask":113.918},{"a":"xm_kiwami","s":2.5,"bid":113.889,"ask":113.914},{"a":"vantage_std","s":3.2,"bid":113.888,"ask":113.92},{"a":"hfm_premium","s":3.2,"bid":113.89,"ask":113.922},{"a":"fxgt_std","s":3.3,"bid":113.887,"ask":113.92}],"XAUUSD":[{"a":"three_pure","s":1.5,"bid":4813.11,"ask":4813.26},{"a":"axi_std","s":1.6,"bid":4812.73,"ask":4812.89},{"a":"icm_std","s":1.6,"bid":4813.8,"ask":4813.96},{"a":"titan_std","s":1.7,"bid":4813.79,"ask":4813.96},{"a":"titan_blade","s":1.7,"bid":4813.62,"ask":4813.79},{"a":"xs_std","s":2.0,"bid":4812.8,"ask":4813.0},{"a":"exness_pro","s":2.0,"bid":4811.551,"ask":4811.747},{"a":"exness_std","s":2.8,"bid":4812.83,"ask":4813.11},{"a":"xm_kiwami","s":3.0,"bid":4812.7,"ask":4813.0},{"a":"hfm_premium","s":3.8,"bid":4811.66,"ask":4812.04},{"a":"fxgt_std","s":3.9,"bid":4813.18,"ask":4813.57},{"a":"vantage_std","s":4.3,"bid":4813.68,"ask":4814.11},{"a":"axiory_std","s":9.7,"bid":4813.02,"ask":4813.99}],"XAGUSD":[{"a":"exness_pro","s":21.0,"bid":79.388,"ask":79.409},{"a":"exness_std","s":30.0,"bid":79.393,"ask":79.423},{"a":"icm_std","s":30.0,"bid":79.378,"ask":79.408},{"a":"axi_std","s":34.0,"bid":79.376,"ask":79.41},{"a":"xs_std","s":40.0,"bid":79.383,"ask":79.423},{"a":"xm_kiwami","s":44.0,"bid":79.382,"ask":79.426},{"a":"three_pure","s":61.0,"bid":79.376,"ask":79.437},{"a":"axiory_std","s":63.0,"bid":79.386,"ask":79.449},{"a":"vantage_std","s":64.0,"bid":79.379,"ask":79.443},{"a":"titan_std","s":65.0,"bid":79.36,"ask":79.425},{"a":"fxgt_std","s":71.0,"bid":79.367,"ask":79.438},{"a":"titan_blade","s":83.0,"bid":79.357,"ask":79.44},{"a":"hfm_premium","s":87.0,"bid":79.34,"ask":79.427}],"BTCUSD":[{"a":"exness_pro","s":9.8,"bid":74761.79,"ask":74771.59},{"a":"axi_std","s":12.0,"bid":74692.68,"ask":74704.68},{"a":"icm_std","s":12.0,"bid":74699.2,"ask":74711.2},{"a":"exness_std","s":14.0,"bid":74714.46,"ask":74728.46},{"a":"three_pure","s":19.0,"bid":74690.0,"ask":74709.0},{"a":"xm_kiwami","s":22.5,"bid":74654.9,"ask":74677.4},{"a":"vantage_std","s":25.0,"bid":74684.65,"ask":74709.67},{"a":"titan_blade","s":36.2,"bid":74705.9,"ask":74742.1},{"a":"xs_std","s":37.0,"bid":74716.12,"ask":74753.12},{"a":"titan_std","s":37.1,"bid":74685.6,"ask":74722.7},{"a":"fxgt_std","s":40.4,"bid":74662.47,"ask":74702.82},{"a":"hfm_premium","s":62.0,"bid":74694.815,"ask":74756.815}],"ETHUSD":[{"a":"exness_pro","s":1.0,"bid":2357.31,"ask":2358.29},{"a":"axi_std","s":1.3,"bid":2350.74,"ask":2351.99},{"a":"exness_std","s":1.4,"bid":2350.89,"ask":2352.29},{"a":"three_pure","s":2.3,"bid":2351.3,"ask":2353.6},{"a":"vantage_std","s":2.5,"bid":2351.57,"ask":2354.03},{"a":"icm_std","s":2.9,"bid":2351.14,"ask":2354.04},{"a":"fxgt_std","s":3.0,"bid":2349.15,"ask":2352.11},{"a":"xm_kiwami","s":3.5,"bid":2348.93,"ask":2352.38},{"a":"xs_std","s":4.6,"bid":2353.7,"ask":2358.3},{"a":"hfm_premium","s":4.9,"bid":2354.275,"ask":2359.135},{"a":"titan_std","s":7.5,"bid":2348.8,"ask":2356.3},{"a":"titan_blade","s":7.5,"bid":2349.6,"ask":2357.1}],"US30":[{"a":"axi_std","s":1.2,"bid":48516.45,"ask":48517.65},{"a":"icm_std","s":1.2,"bid":48518.9,"ask":48520.1},{"a":"exness_pro","s":1.5,"bid":48553.8,"ask":48555.3},{"a":"xs_std","s":2.0,"bid":48516.05,"ask":48518.05},{"a":"exness_std","s":2.1,"bid":48551.7,"ask":48553.8},{"a":"titan_blade","s":3.0,"bid":48543.2,"ask":48546.2},{"a":"vantage_std","s":3.1,"bid":48554.48,"ask":48557.58},{"a":"xm_kiwami","s":3.9,"bid":48515.05,"ask":48518.95},{"a":"three_pure","s":4.0,"bid":48537.0,"ask":48541.0},{"a":"titan_std","s":4.2,"bid":48540.6,"ask":48544.8},{"a":"fxgt_std","s":4.5,"bid":48514.0,"ask":48518.5},{"a":"axiory_std","s":5.4,"bid":48537.24,"ask":48542.64},{"a":"hfm_premium","s":6.8,"bid":48713.93,"ask":48720.74}],"US500":[{"a":"axi_std","s":2.9,"bid":7028.21,"ask":7028.5},{"a":"exness_pro","s":4.5,"bid":7034.02,"ask":7034.47},{"a":"hfm_premium","s":5.0,"bid":7036.0,"ask":7036.5},{"a":"icm_std","s":5.0,"bid":7028.2,"ask":7028.7},{"a":"xm_kiwami","s":5.5,"bid":7027.78,"ask":7028.33},{"a":"vantage_std","s":6.0,"bid":7034.13,"ask":7034.73},{"a":"three_pure","s":6.0,"bid":7030.8,"ask":7031.4},{"a":"exness_std","s":6.4,"bid":7033.73,"ask":7034.37},{"a":"axiory_std","s":7.6,"bid":7030.24,"ask":7031.0},{"a":"titan_blade","s":9.0,"bid":7031.2,"ask":7032.1},{"a":"xs_std","s":11.0,"bid":7028.1,"ask":7029.2},{"a":"titan_std","s":21.0,"bid":7030.1,"ask":7032.2},{"a":"fxgt_std","s":55.4,"bid":7025.58,"ask":7031.12}],"US100":[{"a":"icm_std","s":1.0,"bid":26234.8,"ask":26235.8},{"a":"titan_blade","s":1.0,"bid":26249.5,"ask":26250.5},{"a":"exness_pro","s":1.5,"bid":26267.75,"ask":26269.26},{"a":"vantage_std","s":1.8,"bid":26262.56,"ask":26264.36},{"a":"xs_std","s":1.9,"bid":26234.6,"ask":26236.5},{"a":"xm_kiwami","s":2.0,"bid":26234.15,"ask":26236.1},{"a":"three_pure","s":2.0,"bid":26247.0,"ask":26249.0},{"a":"hfm_premium","s":2.1,"bid":26253.3,"ask":26255.4},{"a":"exness_std","s":2.2,"bid":26266.96,"ask":26269.12},{"a":"titan_std","s":2.2,"bid":26246.6,"ask":26248.8},{"a":"axiory_std","s":2.3,"bid":26245.97,"ask":26248.27},{"a":"axi_std","s":2.5,"bid":26394.63,"ask":26397.13},{"a":"fxgt_std","s":3.4,"bid":26233.46,"ask":26236.86}],"JP225":[{"a":"icm_std","s":5.0,"bid":58516.0,"ask":58521.0},{"a":"exness_pro","s":5.0,"bid":58547.6,"ask":58552.6},{"a":"xm_kiwami","s":6.0,"bid":58507.0,"ask":58513.0},{"a":"exness_std","s":7.1,"bid":58546.6,"ask":58553.7},{"a":"titan_blade","s":8.0,"bid":58538.2,"ask":58546.2},{"a":"vantage_std","s":9.0,"bid":58551.4,"ask":58560.4},{"a":"titan_std","s":9.2,"bid":58525.1,"ask":58534.3},{"a":"xs_std","s":10.0,"bid":58514.0,"ask":58524.0},{"a":"axiory_std","s":11.0,"bid":58524.23,"ask":58535.23},{"a":"fxgt_std","s":12.0,"bid":58510.0,"ask":58522.0},{"a":"hfm_premium","s":13.0,"bid":58544.5,"ask":58557.5},{"a":"three_pure","s":16.0,"bid":58522.0,"ask":58538.0},{"a":"axi_std","s":18.0,"bid":58513.0,"ask":58531.0}],"CRUDE":[{"a":"exness_pro","s":1.4,"bid":87.568,"ask":87.582},{"a":"exness_std","s":2.0,"bid":87.532,"ask":87.552},{"a":"icm_std","s":2.0,"bid":90.74,"ask":90.76},{"a":"axi_std","s":2.5,"bid":87.64,"ask":87.665},{"a":"xs_std","s":3.7,"bid":90.771,"ask":90.808},{"a":"xm_kiwami","s":4.0,"bid":90.71,"ask":90.75},{"a":"titan_blade","s":6.0,"bid":90.67,"ask":90.73},{"a":"titan_std","s":7.0,"bid":90.71,"ask":90.78},{"a":"vantage_std","s":7.3,"bid":90.679,"ask":90.752},{"a":"axiory_std","s":8.6,"bid":90.887,"ask":90.973},{"a":"three_pure","s":11.0,"bid":90.85,"ask":90.96},{"a":"fxgt_std","s":19.0,"bid":90.63,"ask":90.82},{"a":"hfm_premium","s":21.0,"bid":87.39,"ask":87.6}],"NGAS":[{"a":"icm_std","s":1.0,"bid":2.602,"ask":2.603},{"a":"exness_pro","s":8.9,"bid":2.7295,"ask":2.7384},{"a":"axi_std","s":12.0,"bid":2.595,"ask":2.607},{"a":"exness_std","s":12.7,"bid":2.7276,"ask":2.7403},{"a":"titan_blade","s":17.0,"bid":2.594,"ask":2.611},{"a":"titan_std","s":18.0,"bid":2.593,"ask":2.611},{"a":"vantage_std","s":19.0,"bid":2.616,"ask":2.635},{"a":"xm_kiwami","s":23.0,"bid":2.615,"ask":2.638},{"a":"axiory_std","s":54.0,"bid":2.708,"ask":2.762},{"a":"xs_std","s":64.0,"bid":2.702,"ask":2.766},{"a":"fxgt_std","s":85.0,"bid":2.691,"ask":2.776}]}}