{"updated_at":"2026-04-28T12:18:51Z","data":{"USDJPY":[{"a":"titan_blade","s":0.1,"bid":159.736,"ask":159.737},{"a":"icm_raw","s":0.2,"bid":159.717,"ask":159.719},{"a":"hfm_katana","s":0.4,"bid":159.726,"ask":159.73},{"a":"vantage_raw","s":0.5,"bid":159.733,"ask":159.738},{"a":"axiory_nano","s":0.6,"bid":159.735,"ask":159.741},{"a":"exness_pro","s":0.7,"bid":159.73,"ask":159.737},{"a":"axi_std","s":0.7,"bid":159.721,"ask":159.728},{"a":"icm_std","s":0.9,"bid":159.732,"ask":159.741},{"a":"xm_kiwami","s":1.0,"bid":159.719,"ask":159.729},{"a":"exness_std","s":1.0,"bid":159.725,"ask":159.735},{"a":"xs_std","s":1.1,"bid":159.717,"ask":159.728},{"a":"three_pure","s":1.1,"bid":159.719,"ask":159.73},{"a":"titan_std","s":1.2,"bid":159.723,"ask":159.735},{"a":"axiory_std","s":1.6,"bid":159.708,"ask":159.724},{"a":"fxgt_optimus","s":1.8,"bid":159.728,"ask":159.746},{"a":"vantage_std","s":2.0,"bid":159.716,"ask":159.736},{"a":"hfm_premium","s":2.2,"bid":159.715,"ask":159.737},{"a":"xm_std","s":2.2,"bid":159.721,"ask":159.743},{"a":"fxgt_std","s":2.5,"bid":159.714,"ask":159.739}],"EURUSD":[{"a":"vantage_raw","s":0.0,"bid":1.16826,"ask":1.16826},{"a":"titan_blade","s":0.0,"bid":1.16827,"ask":1.16827},{"a":"icm_raw","s":0.1,"bid":1.16849,"ask":1.1685},{"a":"axiory_nano","s":0.4,"bid":1.16839,"ask":1.16843},{"a":"hfm_katana","s":0.6,"bid":1.16834,"ask":1.1684},{"a":"exness_pro","s":0.6,"bid":1.16825,"ask":1.16831},{"a":"axi_std","s":0.7,"bid":1.16842,"ask":1.16849},{"a":"icm_std","s":0.8,"bid":1.16823,"ask":1.16831},{"a":"exness_std","s":0.8,"bid":1.16836,"ask":1.16844},{"a":"three_pure","s":0.8,"bid":1.16844,"ask":1.16852},{"a":"xs_std","s":1.0,"bid":1.1684,"ask":1.1685},{"a":"xm_kiwami","s":1.1,"bid":1.16837,"ask":1.16848},{"a":"titan_std","s":1.2,"bid":1.1684,"ask":1.16852},{"a":"axiory_std","s":1.3,"bid":1.16846,"ask":1.16859},{"a":"vantage_std","s":1.4,"bid":1.16835,"ask":1.16849},{"a":"fxgt_optimus","s":1.4,"bid":1.16818,"ask":1.16832},{"a":"hfm_premium","s":1.7,"bid":1.16833,"ask":1.1685},{"a":"fxgt_std","s":1.9,"bid":1.16834,"ask":1.16853},{"a":"xm_std","s":2.0,"bid":1.16819,"ask":1.16839}],"GBPUSD":[{"a":"icm_raw","s":0.2,"bid":1.34715,"ask":1.34717},{"a":"vantage_raw","s":0.2,"bid":1.34706,"ask":1.34708},{"a":"axiory_nano","s":0.5,"bid":1.34706,"ask":1.34711},{"a":"hfm_katana","s":0.6,"bid":1.34711,"ask":1.34717},{"a":"titan_blade","s":0.6,"bid":1.34701,"ask":1.34707},{"a":"exness_pro","s":0.7,"bid":1.34701,"ask":1.34708},{"a":"axi_std","s":0.8,"bid":1.34714,"ask":1.34722},{"a":"three_pure","s":0.8,"bid":1.34706,"ask":1.34714},{"a":"icm_std","s":0.9,"bid":1.34699,"ask":1.34708},{"a":"xs_std","s":1.0,"bid":1.3471,"ask":1.3472},{"a":"exness_std","s":1.0,"bid":1.3471,"ask":1.3472},{"a":"xm_kiwami","s":1.1,"bid":1.34711,"ask":1.34722},{"a":"axiory_std","s":1.5,"bid":1.34707,"ask":1.34722},{"a":"titan_std","s":1.6,"bid":1.34709,"ask":1.34725},{"a":"fxgt_optimus","s":1.6,"bid":1.34698,"ask":1.34714},{"a":"vantage_std","s":1.8,"bid":1.34708,"ask":1.34726},{"a":"fxgt_std","s":1.9,"bid":1.34706,"ask":1.34725},{"a":"xm_std","s":2.1,"bid":1.34695,"ask":1.34716},{"a":"hfm_premium","s":2.3,"bid":1.34702,"ask":1.34725}],"AUDUSD":[{"a":"icm_raw","s":0.1,"bid":0.71546,"ask":0.71547},{"a":"titan_blade","s":0.1,"bid":0.71546,"ask":0.71547},{"a":"vantage_raw","s":0.4,"bid":0.71548,"ask":0.71552},{"a":"axiory_nano","s":0.5,"bid":0.71546,"ask":0.71551},{"a":"hfm_katana","s":0.6,"bid":0.7155,"ask":0.71556},{"a":"exness_pro","s":0.6,"bid":0.71545,"ask":0.71551},{"a":"axi_std","s":0.7,"bid":0.71548,"ask":0.71555},{"a":"three_pure","s":0.7,"bid":0.71534,"ask":0.71541},{"a":"icm_std","s":0.9,"bid":0.71541,"ask":0.7155},{"a":"exness_std","s":0.9,"bid":0.71543,"ask":0.71552},{"a":"titan_std","s":1.0,"bid":0.7154,"ask":0.7155},{"a":"xs_std","s":1.0,"bid":0.71543,"ask":0.71553},{"a":"xm_kiwami","s":1.3,"bid":0.71543,"ask":0.71556},{"a":"fxgt_optimus","s":1.5,"bid":0.71543,"ask":0.71558},{"a":"axiory_std","s":1.6,"bid":0.71535,"ask":0.71551},{"a":"hfm_premium","s":1.6,"bid":0.7154,"ask":0.71556},{"a":"vantage_std","s":2.1,"bid":0.71537,"ask":0.71558},{"a":"fxgt_std","s":2.1,"bid":0.71535,"ask":0.71556},{"a":"xm_std","s":2.3,"bid":0.71539,"ask":0.71562}],"USDCHF":[{"a":"titan_blade","s":0.0,"bid":0.79088,"ask":0.79088},{"a":"icm_raw","s":0.1,"bid":0.79072,"ask":0.79073},{"a":"vantage_raw","s":0.3,"bid":0.79088,"ask":0.79091},{"a":"hfm_katana","s":0.7,"bid":0.79083,"ask":0.7909},{"a":"three_pure","s":0.7,"bid":0.7907,"ask":0.79077},{"a":"axiory_nano","s":0.7,"bid":0.79078,"ask":0.79085},{"a":"axi_std","s":0.8,"bid":0.79081,"ask":0.79089},{"a":"icm_std","s":0.9,"bid":0.79084,"ask":0.79093},{"a":"exness_pro","s":0.9,"bid":0.79084,"ask":0.79093},{"a":"titan_std","s":1.0,"bid":0.79073,"ask":0.79083},{"a":"xs_std","s":1.1,"bid":0.79074,"ask":0.79085},{"a":"xm_kiwami","s":1.2,"bid":0.79075,"ask":0.79087},{"a":"exness_std","s":1.3,"bid":0.79076,"ask":0.79089},{"a":"fxgt_optimus","s":1.7,"bid":0.7908,"ask":0.79097},{"a":"axiory_std","s":1.9,"bid":0.79063,"ask":0.79082},{"a":"vantage_std","s":1.9,"bid":0.79072,"ask":0.79091},{"a":"fxgt_std","s":1.9,"bid":0.79071,"ask":0.7909},{"a":"hfm_premium","s":2.1,"bid":0.79071,"ask":0.79092},{"a":"xm_std","s":2.2,"bid":0.79076,"ask":0.79098}],"USDCAD":[{"a":"vantage_raw","s":0.0,"bid":1.36748,"ask":1.36748},{"a":"titan_blade","s":0.0,"bid":1.36748,"ask":1.36748},{"a":"icm_raw","s":0.3,"bid":1.36715,"ask":1.36718},{"a":"three_pure","s":0.6,"bid":1.3672,"ask":1.36726},{"a":"axiory_nano","s":0.7,"bid":1.36725,"ask":1.36732},{"a":"axi_std","s":0.8,"bid":1.36718,"ask":1.36726},{"a":"hfm_katana","s":0.9,"bid":1.36749,"ask":1.36758},{"a":"icm_std","s":1.0,"bid":1.36743,"ask":1.36753},{"a":"titan_std","s":1.0,"bid":1.36719,"ask":1.36729},{"a":"exness_pro","s":1.0,"bid":1.36742,"ask":1.36752},{"a":"xs_std","s":1.3,"bid":1.3672,"ask":1.36733},{"a":"exness_std","s":1.4,"bid":1.36721,"ask":1.36735},{"a":"fxgt_optimus","s":1.6,"bid":1.36744,"ask":1.3676},{"a":"axiory_std","s":1.8,"bid":1.36701,"ask":1.36719},{"a":"xm_kiwami","s":2.0,"bid":1.36716,"ask":1.36736},{"a":"hfm_premium","s":2.1,"bid":1.36715,"ask":1.36736},{"a":"vantage_std","s":2.2,"bid":1.36715,"ask":1.36737},{"a":"fxgt_std","s":2.7,"bid":1.36713,"ask":1.3674},{"a":"xm_std","s":2.8,"bid":1.36735,"ask":1.36763}],"EURJPY":[{"a":"vantage_raw","s":0.0,"bid":186.581,"ask":186.581},{"a":"icm_raw","s":0.1,"bid":186.598,"ask":186.599},{"a":"titan_blade","s":0.1,"bid":186.582,"ask":186.583},{"a":"axi_std","s":0.8,"bid":186.594,"ask":186.602},{"a":"axiory_nano","s":0.8,"bid":186.601,"ask":186.609},{"a":"three_pure","s":0.9,"bid":186.597,"ask":186.606},{"a":"icm_std","s":1.1,"bid":186.577,"ask":186.588},{"a":"titan_std","s":1.1,"bid":186.598,"ask":186.609},{"a":"exness_pro","s":1.1,"bid":186.578,"ask":186.589},{"a":"hfm_katana","s":1.3,"bid":186.58,"ask":186.593},{"a":"xs_std","s":1.5,"bid":186.59,"ask":186.605},{"a":"exness_std","s":1.6,"bid":186.588,"ask":186.604},{"a":"axiory_std","s":1.9,"bid":186.597,"ask":186.616},{"a":"xm_kiwami","s":2.0,"bid":186.583,"ask":186.603},{"a":"hfm_premium","s":2.2,"bid":186.584,"ask":186.606},{"a":"fxgt_optimus","s":2.6,"bid":186.571,"ask":186.597},{"a":"vantage_std","s":3.0,"bid":186.583,"ask":186.613},{"a":"fxgt_std","s":3.0,"bid":186.584,"ask":186.614},{"a":"xm_std","s":3.3,"bid":186.566,"ask":186.599}],"GBPJPY":[{"a":"icm_raw","s":0.8,"bid":215.16,"ask":215.168},{"a":"vantage_raw","s":1.0,"bid":215.168,"ask":215.178},{"a":"axiory_nano","s":1.3,"bid":215.158,"ask":215.171},{"a":"icm_std","s":1.5,"bid":215.162,"ask":215.177},{"a":"hfm_katana","s":1.5,"bid":215.177,"ask":215.192},{"a":"axi_std","s":1.5,"bid":215.166,"ask":215.181},{"a":"three_pure","s":1.5,"bid":215.16,"ask":215.175},{"a":"xs_std","s":1.6,"bid":215.165,"ask":215.181},{"a":"titan_blade","s":1.7,"bid":215.162,"ask":215.179},{"a":"exness_pro","s":1.9,"bid":215.161,"ask":215.18},{"a":"axiory_std","s":2.2,"bid":215.158,"ask":215.18},{"a":"xm_kiwami","s":2.5,"bid":215.165,"ask":215.19},{"a":"exness_std","s":2.7,"bid":215.173,"ask":215.2},{"a":"hfm_premium","s":2.8,"bid":215.157,"ask":215.185},{"a":"fxgt_std","s":3.2,"bid":215.163,"ask":215.195},{"a":"titan_std","s":3.3,"bid":215.164,"ask":215.197},{"a":"fxgt_optimus","s":3.3,"bid":215.159,"ask":215.192},{"a":"xm_std","s":3.7,"bid":215.15,"ask":215.187},{"a":"vantage_std","s":5.2,"bid":215.15,"ask":215.202}],"AUDJPY":[{"a":"titan_blade","s":0.3,"bid":114.281,"ask":114.284},{"a":"icm_raw","s":0.4,"bid":114.269,"ask":114.273},{"a":"axiory_nano","s":0.5,"bid":114.281,"ask":114.286},{"a":"vantage_raw","s":0.7,"bid":114.286,"ask":114.293},{"a":"three_pure","s":0.8,"bid":114.256,"ask":114.264},{"a":"axi_std","s":1.1,"bid":114.277,"ask":114.288},{"a":"icm_std","s":1.3,"bid":114.276,"ask":114.289},{"a":"hfm_katana","s":1.3,"bid":114.285,"ask":114.298},{"a":"exness_pro","s":1.3,"bid":114.277,"ask":114.29},{"a":"axiory_std","s":1.7,"bid":114.265,"ask":114.282},{"a":"titan_std","s":1.7,"bid":114.267,"ask":114.284},{"a":"xs_std","s":1.7,"bid":114.269,"ask":114.286},{"a":"exness_std","s":1.9,"bid":114.271,"ask":114.29},{"a":"xm_kiwami","s":2.1,"bid":114.27,"ask":114.291},{"a":"fxgt_optimus","s":2.6,"bid":114.275,"ask":114.301},{"a":"hfm_premium","s":2.8,"bid":114.265,"ask":114.293},{"a":"fxgt_std","s":3.0,"bid":114.259,"ask":114.289},{"a":"vantage_std","s":3.2,"bid":114.261,"ask":114.293},{"a":"xm_std","s":3.3,"bid":114.272,"ask":114.305}],"XAUUSD":[{"a":"hfm_katana","s":0.9,"bid":4581.54,"ask":4581.63},{"a":"icm_raw","s":1.0,"bid":4583.31,"ask":4583.41},{"a":"titan_blade","s":1.1,"bid":4581.97,"ask":4582.08},{"a":"icm_std","s":1.5,"bid":4581.99,"ask":4582.14},{"a":"axi_std","s":1.5,"bid":4583.25,"ask":4583.4},{"a":"three_pure","s":1.5,"bid":4578.81,"ask":4578.96},{"a":"vantage_raw","s":1.5,"bid":4581.99,"ask":4582.14},{"a":"titan_std","s":1.9,"bid":4583.4,"ask":4583.59},{"a":"xs_std","s":2.0,"bid":4584.07,"ask":4584.27},{"a":"exness_pro","s":2.0,"bid":4582.137,"ask":4582.333},{"a":"xm_kiwami","s":2.7,"bid":4585.06,"ask":4585.33},{"a":"exness_std","s":2.8,"bid":4583.656,"ask":4583.936},{"a":"hfm_premium","s":3.4,"bid":4583.25,"ask":4583.59},{"a":"fxgt_std","s":3.6,"bid":4583.78,"ask":4584.14},{"a":"fxgt_optimus","s":3.7,"bid":4581.76,"ask":4582.13},{"a":"vantage_std","s":4.2,"bid":4584.07,"ask":4584.49},{"a":"xm_std","s":5.0,"bid":4581.62,"ask":4582.12},{"a":"axiory_std","s":6.6,"bid":4582.02,"ask":4582.68},{"a":"axiory_nano","s":6.6,"bid":4584.77,"ask":4585.43}],"XAGUSD":[{"a":"exness_pro","s":21.0,"bid":72.806,"ask":72.827},{"a":"icm_raw","s":29.0,"bid":72.952,"ask":72.981},{"a":"axi_std","s":29.0,"bid":72.912,"ask":72.941},{"a":"exness_std","s":30.0,"bid":72.859,"ask":72.889},{"a":"vantage_raw","s":35.0,"bid":72.809,"ask":72.844},{"a":"icm_std","s":37.0,"bid":72.809,"ask":72.846},{"a":"hfm_katana","s":37.0,"bid":72.781,"ask":72.818},{"a":"three_pure","s":43.0,"bid":72.843,"ask":72.886},{"a":"vantage_std","s":44.0,"bid":72.891,"ask":72.935},{"a":"xm_kiwami","s":50.0,"bid":72.894,"ask":72.944},{"a":"xs_std","s":52.0,"bid":72.909,"ask":72.961},{"a":"axiory_nano","s":53.0,"bid":72.902,"ask":72.955},{"a":"titan_blade","s":61.0,"bid":72.797,"ask":72.858},{"a":"titan_std","s":66.0,"bid":72.929,"ask":72.995},{"a":"axiory_std","s":69.0,"bid":72.935,"ask":73.004},{"a":"xm_std","s":71.0,"bid":72.788,"ask":72.859},{"a":"hfm_premium","s":79.0,"bid":72.866,"ask":72.945},{"a":"fxgt_optimus","s":86.0,"bid":72.779,"ask":72.865},{"a":"fxgt_std","s":106.0,"bid":72.869,"ask":72.975}],"BTCUSD":[{"a":"exness_pro","s":9.8,"bid":76264.38,"ask":76274.18},{"a":"hfm_katana","s":10.0,"bid":76239.676,"ask":76249.656},{"a":"icm_std","s":12.0,"bid":76269.07,"ask":76281.07},{"a":"icm_raw","s":12.0,"bid":76254.17,"ask":76266.17},{"a":"axi_std","s":12.0,"bid":76241.08,"ask":76253.08},{"a":"exness_std","s":14.0,"bid":76264.89,"ask":76278.89},{"a":"three_pure","s":19.0,"bid":76217.0,"ask":76236.0},{"a":"xm_kiwami","s":22.5,"bid":76262.7,"ask":76285.2},{"a":"vantage_raw","s":25.0,"bid":76261.53,"ask":76286.49},{"a":"vantage_std","s":25.1,"bid":76263.26,"ask":76288.34},{"a":"fxgt_optimus","s":28.7,"bid":76302.07,"ask":76330.72},{"a":"fxgt_std","s":33.7,"bid":76306.62,"ask":76340.33},{"a":"titan_blade","s":36.1,"bid":76248.5,"ask":76284.6},{"a":"xs_std","s":38.2,"bid":76228.29,"ask":76266.45},{"a":"titan_std","s":38.5,"bid":76230.5,"ask":76269.0},{"a":"xm_std","s":50.0,"bid":76252.0,"ask":76302.0},{"a":"hfm_premium","s":62.0,"bid":76216.273,"ask":76278.273}],"ETHUSD":[{"a":"hfm_katana","s":1.0,"bid":2276.236,"ask":2277.235},{"a":"exness_pro","s":1.0,"bid":2277.4,"ask":2278.38},{"a":"axi_std","s":1.3,"bid":2275.295,"ask":2276.545},{"a":"exness_std","s":1.4,"bid":2276.23,"ask":2277.63},{"a":"three_pure","s":2.1,"bid":2274.3,"ask":2276.4},{"a":"fxgt_optimus","s":2.3,"bid":2277.05,"ask":2279.39},{"a":"vantage_std","s":2.5,"bid":2275.48,"ask":2278.01},{"a":"vantage_raw","s":2.5,"bid":2276.45,"ask":2278.96},{"a":"fxgt_std","s":2.7,"bid":2276.16,"ask":2278.9},{"a":"icm_std","s":2.9,"bid":2276.23,"ask":2279.13},{"a":"icm_raw","s":2.9,"bid":2274.87,"ask":2277.77},{"a":"xm_kiwami","s":3.5,"bid":2275.17,"ask":2278.62},{"a":"xs_std","s":4.6,"bid":2273.66,"ask":2278.26},{"a":"hfm_premium","s":4.9,"bid":2273.525,"ask":2278.385},{"a":"xm_std","s":4.9,"bid":2274.95,"ask":2279.87},{"a":"titan_std","s":7.5,"bid":2272.4,"ask":2279.9},{"a":"titan_blade","s":7.5,"bid":2273.6,"ask":2281.1}],"US30":[{"a":"axi_std","s":1.0,"bid":49259.75,"ask":49260.75},{"a":"icm_std","s":1.2,"bid":49261.7,"ask":49262.9},{"a":"icm_raw","s":1.2,"bid":49263.7,"ask":49264.9},{"a":"exness_pro","s":1.5,"bid":49303.7,"ask":49305.2},{"a":"hfm_katana","s":1.9,"bid":49310.0,"ask":49311.9},{"a":"xs_std","s":2.0,"bid":49262.25,"ask":49264.25},{"a":"exness_std","s":2.1,"bid":49305.6,"ask":49307.7},{"a":"titan_blade","s":2.5,"bid":49295.0,"ask":49297.5},{"a":"three_pure","s":3.0,"bid":49284.0,"ask":49287.0},{"a":"fxgt_optimus","s":3.6,"bid":49263.44,"ask":49267.06},{"a":"titan_std","s":3.7,"bid":49293.4,"ask":49297.1},{"a":"vantage_raw","s":3.7,"bid":49305.19,"ask":49308.91},{"a":"xm_kiwami","s":3.9,"bid":49262.55,"ask":49266.45},{"a":"axiory_nano","s":3.9,"bid":49285.01,"ask":49288.91},{"a":"fxgt_std","s":4.5,"bid":49262.06,"ask":49266.56},{"a":"vantage_std","s":4.7,"bid":49300.69,"ask":49305.41},{"a":"axiory_std","s":4.9,"bid":49295.81,"ask":49300.71},{"a":"xm_std","s":5.5,"bid":49261.75,"ask":49267.25},{"a":"hfm_premium","s":6.8,"bid":49414.11,"ask":49420.92}],"US500":[{"a":"axi_std","s":3.0,"bid":7126.1,"ask":7126.4},{"a":"icm_std","s":5.0,"bid":7127.1,"ask":7127.6},{"a":"icm_raw","s":5.0,"bid":7127.0,"ask":7127.5},{"a":"three_pure","s":5.0,"bid":7129.8,"ask":7130.3},{"a":"hfm_premium","s":5.0,"bid":7135.8,"ask":7136.3},{"a":"xm_kiwami","s":5.5,"bid":7126.53,"ask":7127.08},{"a":"vantage_std","s":6.0,"bid":7136.48,"ask":7137.08},{"a":"exness_pro","s":6.0,"bid":7137.52,"ask":7138.12},{"a":"axiory_nano","s":6.0,"bid":7130.24,"ask":7130.84},{"a":"vantage_raw","s":6.0,"bid":7137.98,"ask":7138.58},{"a":"hfm_katana","s":6.2,"bid":7137.5,"ask":7138.12},{"a":"axiory_std","s":7.0,"bid":7131.52,"ask":7132.22},{"a":"xm_std","s":7.0,"bid":7127.33,"ask":7128.03},{"a":"titan_blade","s":8.0,"bid":7132.1,"ask":7132.9},{"a":"exness_std","s":8.6,"bid":7136.39,"ask":7137.25},{"a":"xs_std","s":13.0,"bid":7125.8,"ask":7127.1},{"a":"titan_std","s":20.0,"bid":7130.9,"ask":7132.9},{"a":"fxgt_optimus","s":24.6,"bid":7126.22,"ask":7128.68},{"a":"fxgt_std","s":57.6,"bid":7123.57,"ask":7129.33}],"US100":[{"a":"icm_std","s":1.0,"bid":26965.9,"ask":26966.9},{"a":"icm_raw","s":1.0,"bid":26967.9,"ask":26968.9},{"a":"titan_blade","s":1.0,"bid":26986.0,"ask":26987.0},{"a":"hfm_katana","s":1.5,"bid":26991.45,"ask":26992.95},{"a":"exness_pro","s":1.7,"bid":26989.49,"ask":26991.17},{"a":"vantage_std","s":1.8,"bid":26984.7,"ask":26986.5},{"a":"vantage_raw","s":1.8,"bid":26992.95,"ask":26994.75},{"a":"xs_std","s":1.9,"bid":26961.7,"ask":26963.6},{"a":"xm_kiwami","s":2.0,"bid":26961.27,"ask":26963.22},{"a":"three_pure","s":2.0,"bid":26975.0,"ask":26977.0},{"a":"axiory_nano","s":2.0,"bid":26978.34,"ask":26980.34},{"a":"axiory_std","s":2.1,"bid":26984.95,"ask":26987.05},{"a":"titan_std","s":2.2,"bid":26984.4,"ask":26986.6},{"a":"exness_std","s":2.4,"bid":26984.61,"ask":26987.01},{"a":"hfm_premium","s":2.4,"bid":26982.5,"ask":26984.9},{"a":"axi_std","s":2.5,"bid":27094.38,"ask":27096.88},{"a":"xm_std","s":2.6,"bid":26966.08,"ask":26968.68},{"a":"fxgt_optimus","s":3.4,"bid":26965.71,"ask":26969.14},{"a":"fxgt_std","s":3.4,"bid":26960.59,"ask":26963.99}],"JP225":[{"a":"icm_std","s":4.0,"bid":59279.0,"ask":59283.0},{"a":"icm_raw","s":4.0,"bid":59274.0,"ask":59278.0},{"a":"exness_pro","s":4.2,"bid":59295.8,"ask":59300.0},{"a":"xm_kiwami","s":6.0,"bid":59275.0,"ask":59281.0},{"a":"exness_std","s":6.0,"bid":59290.4,"ask":59296.4},{"a":"xm_std","s":8.0,"bid":59294.0,"ask":59302.0},{"a":"titan_blade","s":8.0,"bid":59282.0,"ask":59290.0},{"a":"titan_std","s":9.2,"bid":59273.9,"ask":59283.1},{"a":"xs_std","s":10.0,"bid":59271.5,"ask":59281.5},{"a":"axiory_nano","s":10.0,"bid":59243.02,"ask":59253.02},{"a":"axiory_std","s":11.0,"bid":59270.52,"ask":59281.52},{"a":"vantage_raw","s":11.0,"bid":59312.66,"ask":59323.66},{"a":"hfm_katana","s":11.2,"bid":59322.4,"ask":59333.6},{"a":"fxgt_optimus","s":12.0,"bid":59286.0,"ask":59298.0},{"a":"fxgt_std","s":14.0,"bid":59270.0,"ask":59284.0},{"a":"vantage_std","s":16.0,"bid":59282.66,"ask":59298.66},{"a":"three_pure","s":16.0,"bid":59239.0,"ask":59255.0},{"a":"hfm_premium","s":16.0,"bid":59280.0,"ask":59296.0},{"a":"axi_std","s":18.0,"bid":59265.5,"ask":59283.5}],"CRUDE":[{"a":"exness_pro","s":1.4,"bid":98.346,"ask":98.36},{"a":"icm_std","s":2.0,"bid":102.25,"ask":102.27},{"a":"icm_raw","s":2.0,"bid":102.26,"ask":102.28},{"a":"exness_std","s":2.0,"bid":98.38,"ask":98.4},{"a":"axi_std","s":2.5,"bid":98.375,"ask":98.4},{"a":"xs_std","s":3.8,"bid":102.247,"ask":102.285},{"a":"xm_kiwami","s":4.0,"bid":102.84,"ask":102.88},{"a":"xm_std","s":5.0,"bid":102.72,"ask":102.77},{"a":"titan_blade","s":6.0,"bid":102.24,"ask":102.3},{"a":"vantage_raw","s":6.7,"bid":102.123,"ask":102.19},{"a":"titan_std","s":7.0,"bid":102.25,"ask":102.32},{"a":"vantage_std","s":7.3,"bid":102.24,"ask":102.313},{"a":"axiory_std","s":7.6,"bid":103.064,"ask":103.14},{"a":"axiory_nano","s":7.6,"bid":103.186,"ask":103.262},{"a":"three_pure","s":9.0,"bid":103.14,"ask":103.23},{"a":"hfm_katana","s":11.0,"bid":102.08,"ask":102.19},{"a":"hfm_premium","s":13.0,"bid":100.48,"ask":100.61},{"a":"fxgt_optimus","s":16.0,"bid":102.07,"ask":102.23},{"a":"fxgt_std","s":20.0,"bid":102.16,"ask":102.36}],"NGAS":[{"a":"icm_std","s":5.0,"bid":2.587,"ask":2.592},{"a":"icm_raw","s":5.0,"bid":2.598,"ask":2.603},{"a":"vantage_std","s":7.0,"bid":2.601,"ask":2.608},{"a":"vantage_raw","s":7.0,"bid":2.599,"ask":2.606},{"a":"exness_pro","s":7.3,"bid":2.7795,"ask":2.7868},{"a":"exness_std","s":10.5,"bid":2.7784,"ask":2.7889},{"a":"xm_kiwami","s":11.0,"bid":2.596,"ask":2.607},{"a":"axi_std","s":11.0,"bid":2.712,"ask":2.723},{"a":"xm_std","s":16.0,"bid":2.594,"ask":2.61},{"a":"titan_blade","s":21.0,"bid":2.579,"ask":2.6},{"a":"titan_std","s":22.0,"bid":2.589,"ask":2.611},{"a":"axiory_std","s":25.0,"bid":2.783,"ask":2.808},{"a":"axiory_nano","s":25.0,"bid":2.772,"ask":2.797},{"a":"xs_std","s":37.0,"bid":2.767,"ask":2.804},{"a":"fxgt_optimus","s":38.0,"bid":2.765,"ask":2.803},{"a":"fxgt_std","s":63.0,"bid":2.754,"ask":2.817}]}}